{"match_id":"269b3374-03ed-4605-91ea-7994099df5a1.nakama-0","map_id":"AmbroseValley","duration_ms":0,"players":[{"user_id":"10648aa3-b215-4c52-9577-5c5689a08939","is_bot":false,"events":110}],"events":[{"user_id":"10648aa3-b215-4c52-9577-5c5689a08939","event":"Position","category":"move_human","px":693.2,"py":242.6,"ts_relative":0,"is_bot":false},{"user_id":"10648aa3-b215-4c52-9577-5c5689a08939","event":"Position","category":"move_human","px":673.0,"py":254.1,"ts_relative":0,"is_bot":false},{"user_id":"10648aa3-b215-4c52-9577-5c5689a08939","event":"Loot","category":"loot","px":641.0,"py":255.8,"ts_relative":0,"is_bot":false},{"user_id":"10648aa3-b215-4c52-9577-5c5689a08939","event":"Position","category":"move_human","px":641.0,"py":255.8,"ts_relative":0,"is_bot":false},{"user_id":"10648aa3-b215-4c52-9577-5c5689a08939","event":"Loot","category":"loot","px":641.0,"py":255.8,"ts_relative":0,"is_bot":false},{"user_id":"10648aa3-b215-4c52-9577-5c5689a08939","event":"Position","category":"move_human","px":632.3,"py":260.6,"ts_relative":0,"is_bot":false},{"user_id":"10648aa3-b215-4c52-9577-5c5689a08939","event":"Loot","category":"loot","px":638.6,"py":252.4,"ts_relative":0,"is_bot":false},{"user_id":"10648aa3-b215-4c52-9577-5c5689a08939","event":"Position","category":"move_human","px":638.6,"py":252.4,"ts_relative":0,"is_bot":false},{"user_id":"10648aa3-b215-4c52-9577-5c5689a08939","event":"Position","category":"move_human","px":611.6,"py":259.5,"ts_relative":0,"is_bot":false},{"user_id":"10648aa3-b215-4c52-9577-5c5689a08939","event":"Position","category":"move_human","px":599.9,"py":294.4,"ts_relative":0,"is_bot":false},{"user_id":"10648aa3-b215-4c52-9577-5c5689a08939","event":"Position","category":"move_human","px":596.6,"py":314.1,"ts_relative":0,"is_bot":false},{"user_id":"10648aa3-b215-4c52-9577-5c5689a08939","event":"Loot","category":"loot","px":596.6,"py":314.1,"ts_relative":0,"is_bot":false},{"user_id":"10648aa3-b215-4c52-9577-5c5689a08939","event":"Loot","category":"loot","px":602.0,"py":323.4,"ts_relative":0,"is_bot":false},{"user_id":"10648aa3-b215-4c52-9577-5c5689a08939","event":"Loot","category":"loot","px":602.0,"py":323.4,"ts_relative":0,"is_bot":false},{"user_id":"10648aa3-b215-4c52-9577-5c5689a08939","event":"Position","category":"move_human","px":602.0,"py":323.4,"ts_relative":0,"is_bot":false},{"user_id":"10648aa3-b215-4c52-9577-5c5689a08939","event":"Loot","category":"loot","px":602.0,"py":323.4,"ts_relative":0,"is_bot":false},{"user_id":"10648aa3-b215-4c52-9577-5c5689a08939","event":"Position","category":"move_human","px":590.0,"py":316.9,"ts_relative":0,"is_bot":false},{"user_id":"10648aa3-b215-4c52-9577-5c5689a08939","event":"Position","category":"move_human","px":557.8,"py":323.4,"ts_relative":0,"is_bot":false},{"user_id":"10648aa3-b215-4c52-9577-5c5689a08939","event":"Position","category":"move_human","px":530.3,"py":341.6,"ts_relative":0,"is_bot":false},{"user_id":"10648aa3-b215-4c52-9577-5c5689a08939","event":"Position","category":"move_human","px":522.0,"py":341.3,"ts_relative":0,"is_bot":false},{"user_id":"10648aa3-b215-4c52-9577-5c5689a08939","event":"Loot","category":"loot","px":522.0,"py":341.3,"ts_relative":0,"is_bot":false},{"user_id":"10648aa3-b215-4c52-9577-5c5689a08939","event":"Position","category":"move_human","px":502.4,"py":331.3,"ts_relative":0,"is_bot":false},{"user_id":"10648aa3-b215-4c52-9577-5c5689a08939","event":"Position","category":"move_human","px":480.2,"py":312.1,"ts_relative":0,"is_bot":false},{"user_id":"10648aa3-b215-4c52-9577-5c5689a08939","event":"Position","category":"move_human","px":457.8,"py":293.8,"ts_relative":0,"is_bot":false},{"user_id":"10648aa3-b215-4c52-9577-5c5689a08939","event":"Position","category":"move_human","px":457.0,"py":282.5,"ts_relative":0,"is_bot":false},{"user_id":"10648aa3-b215-4c52-9577-5c5689a08939","event":"Position","category":"move_human","px":458.0,"py":264.4,"ts_relative":0,"is_bot":false},{"user_id":"10648aa3-b215-4c52-9577-5c5689a08939","event":"Position","category":"move_human","px":481.6,"py":264.0,"ts_relative":0,"is_bot":false},{"user_id":"10648aa3-b215-4c52-9577-5c5689a08939","event":"Position","category":"move_human","px":496.3,"py":260.1,"ts_relative":0,"is_bot":false},{"user_id":"10648aa3-b215-4c52-9577-5c5689a08939","event":"Position","category":"move_human","px":490.9,"py":246.7,"ts_relative":0,"is_bot":false},{"user_id":"10648aa3-b215-4c52-9577-5c5689a08939","event":"Position","category":"move_human","px":489.4,"py":256.8,"ts_relative":0,"is_bot":false},{"user_id":"10648aa3-b215-4c52-9577-5c5689a08939","event":"Position","category":"move_human","px":485.2,"py":232.0,"ts_relative":0,"is_bot":false},{"user_id":"10648aa3-b215-4c52-9577-5c5689a08939","event":"Position","category":"move_human","px":468.6,"py":229.0,"ts_relative":0,"is_bot":false},{"user_id":"10648aa3-b215-4c52-9577-5c5689a08939","event":"Position","category":"move_human","px":466.0,"py":230.0,"ts_relative":0,"is_bot":false},{"user_id":"10648aa3-b215-4c52-9577-5c5689a08939","event":"BotKill","category":"combat","px":467.1,"py":230.4,"ts_relative":0,"is_bot":false},{"user_id":"10648aa3-b215-4c52-9577-5c5689a08939","event":"Position","category":"move_human","px":467.4,"py":229.9,"ts_relative":0,"is_bot":false},{"user_id":"10648aa3-b215-4c52-9577-5c5689a08939","event":"Loot","category":"loot","px":466.2,"py":232.6,"ts_relative":0,"is_bot":false},{"user_id":"10648aa3-b215-4c52-9577-5c5689a08939","event":"Loot","category":"loot","px":466.2,"py":232.6,"ts_relative":0,"is_bot":false},{"user_id":"10648aa3-b215-4c52-9577-5c5689a08939","event":"Position","category":"move_human","px":475.6,"py":248.8,"ts_relative":0,"is_bot":false},{"user_id":"10648aa3-b215-4c52-9577-5c5689a08939","event":"Position","category":"move_human","px":478.1,"py":257.0,"ts_relative":0,"is_bot":false},{"user_id":"10648aa3-b215-4c52-9577-5c5689a08939","event":"Position","category":"move_human","px":486.0,"py":244.5,"ts_relative":0,"is_bot":false},{"user_id":"10648aa3-b215-4c52-9577-5c5689a08939","event":"BotKill","category":"combat","px":495.8,"py":237.8,"ts_relative":0,"is_bot":false},{"user_id":"10648aa3-b215-4c52-9577-5c5689a08939","event":"Loot","category":"loot","px":499.4,"py":237.9,"ts_relative":0,"is_bot":false},{"user_id":"10648aa3-b215-4c52-9577-5c5689a08939","event":"Loot","category":"loot","px":499.4,"py":237.9,"ts_relative":0,"is_bot":false},{"user_id":"10648aa3-b215-4c52-9577-5c5689a08939","event":"Position","category":"move_human","px":499.4,"py":237.9,"ts_relative":0,"is_bot":false},{"user_id":"10648aa3-b215-4c52-9577-5c5689a08939","event":"Position","category":"move_human","px":483.9,"py":242.4,"ts_relative":0,"is_bot":false},{"user_id":"10648aa3-b215-4c52-9577-5c5689a08939","event":"Position","category":"move_human","px":457.0,"py":256.0,"ts_relative":0,"is_bot":false},{"user_id":"10648aa3-b215-4c52-9577-5c5689a08939","event":"Position","category":"move_human","px":453.7,"py":260.2,"ts_relative":0,"is_bot":false},{"user_id":"10648aa3-b215-4c52-9577-5c5689a08939","event":"BotKill","category":"combat","px":453.7,"py":260.2,"ts_relative":0,"is_bot":false},{"user_id":"10648aa3-b215-4c52-9577-5c5689a08939","event":"Position","category":"move_human","px":456.1,"py":259.2,"ts_relative":0,"is_bot":false},{"user_id":"10648aa3-b215-4c52-9577-5c5689a08939","event":"Position","category":"move_human","px":452.0,"py":251.2,"ts_relative":0,"is_bot":false},{"user_id":"10648aa3-b215-4c52-9577-5c5689a08939","event":"Position","category":"move_human","px":456.6,"py":251.0,"ts_relative":0,"is_bot":false},{"user_id":"10648aa3-b215-4c52-9577-5c5689a08939","event":"BotKill","category":"combat","px":456.3,"py":256.4,"ts_relative":0,"is_bot":false},{"user_id":"10648aa3-b215-4c52-9577-5c5689a08939","event":"Position","category":"move_human","px":457.2,"py":264.9,"ts_relative":0,"is_bot":false},{"user_id":"10648aa3-b215-4c52-9577-5c5689a08939","event":"Loot","category":"loot","px":459.3,"py":277.6,"ts_relative":0,"is_bot":false},{"user_id":"10648aa3-b215-4c52-9577-5c5689a08939","event":"Loot","category":"loot","px":459.3,"py":277.6,"ts_relative":0,"is_bot":false},{"user_id":"10648aa3-b215-4c52-9577-5c5689a08939","event":"Position","category":"move_human","px":459.3,"py":277.6,"ts_relative":0,"is_bot":false},{"user_id":"10648aa3-b215-4c52-9577-5c5689a08939","event":"BotKill","category":"combat","px":444.7,"py":280.3,"ts_relative":0,"is_bot":false},{"user_id":"10648aa3-b215-4c52-9577-5c5689a08939","event":"Position","category":"move_human","px":442.0,"py":280.8,"ts_relative":0,"is_bot":false},{"user_id":"10648aa3-b215-4c52-9577-5c5689a08939","event":"Loot","category":"loot","px":428.9,"py":274.0,"ts_relative":0,"is_bot":false},{"user_id":"10648aa3-b215-4c52-9577-5c5689a08939","event":"Loot","category":"loot","px":428.9,"py":274.0,"ts_relative":0,"is_bot":false},{"user_id":"10648aa3-b215-4c52-9577-5c5689a08939","event":"Position","category":"move_human","px":428.9,"py":274.0,"ts_relative":0,"is_bot":false},{"user_id":"10648aa3-b215-4c52-9577-5c5689a08939","event":"Loot","category":"loot","px":428.9,"py":274.0,"ts_relative":0,"is_bot":false},{"user_id":"10648aa3-b215-4c52-9577-5c5689a08939","event":"Loot","category":"loot","px":425.2,"py":276.9,"ts_relative":0,"is_bot":false},{"user_id":"10648aa3-b215-4c52-9577-5c5689a08939","event":"Position","category":"move_human","px":425.2,"py":276.9,"ts_relative":0,"is_bot":false},{"user_id":"10648aa3-b215-4c52-9577-5c5689a08939","event":"Loot","category":"loot","px":424.3,"py":280.8,"ts_relative":0,"is_bot":false},{"user_id":"10648aa3-b215-4c52-9577-5c5689a08939","event":"Position","category":"move_human","px":427.6,"py":272.0,"ts_relative":0,"is_bot":false},{"user_id":"10648aa3-b215-4c52-9577-5c5689a08939","event":"Position","category":"move_human","px":427.9,"py":275.5,"ts_relative":0,"is_bot":false},{"user_id":"10648aa3-b215-4c52-9577-5c5689a08939","event":"Loot","category":"loot","px":424.1,"py":290.5,"ts_relative":0,"is_bot":false},{"user_id":"10648aa3-b215-4c52-9577-5c5689a08939","event":"Position","category":"move_human","px":425.4,"py":286.5,"ts_relative":0,"is_bot":false},{"user_id":"10648aa3-b215-4c52-9577-5c5689a08939","event":"Position","category":"move_human","px":428.4,"py":273.7,"ts_relative":0,"is_bot":false},{"user_id":"10648aa3-b215-4c52-9577-5c5689a08939","event":"Position","category":"move_human","px":444.4,"py":265.5,"ts_relative":0,"is_bot":false},{"user_id":"10648aa3-b215-4c52-9577-5c5689a08939","event":"Position","category":"move_human","px":448.7,"py":242.9,"ts_relative":0,"is_bot":false},{"user_id":"10648aa3-b215-4c52-9577-5c5689a08939","event":"Position","category":"move_human","px":449.5,"py":234.4,"ts_relative":0,"is_bot":false},{"user_id":"10648aa3-b215-4c52-9577-5c5689a08939","event":"Position","category":"move_human","px":466.7,"py":231.1,"ts_relative":0,"is_bot":false},{"user_id":"10648aa3-b215-4c52-9577-5c5689a08939","event":"Position","category":"move_human","px":463.1,"py":228.6,"ts_relative":0,"is_bot":false},{"user_id":"10648aa3-b215-4c52-9577-5c5689a08939","event":"Loot","category":"loot","px":463.4,"py":229.4,"ts_relative":0,"is_bot":false},{"user_id":"10648aa3-b215-4c52-9577-5c5689a08939","event":"Loot","category":"loot","px":461.4,"py":227.8,"ts_relative":0,"is_bot":false},{"user_id":"10648aa3-b215-4c52-9577-5c5689a08939","event":"Position","category":"move_human","px":464.7,"py":220.8,"ts_relative":0,"is_bot":false},{"user_id":"10648aa3-b215-4c52-9577-5c5689a08939","event":"Loot","category":"loot","px":462.2,"py":222.4,"ts_relative":0,"is_bot":false},{"user_id":"10648aa3-b215-4c52-9577-5c5689a08939","event":"Position","category":"move_human","px":462.2,"py":211.5,"ts_relative":0,"is_bot":false},{"user_id":"10648aa3-b215-4c52-9577-5c5689a08939","event":"Position","category":"move_human","px":471.6,"py":215.7,"ts_relative":0,"is_bot":false},{"user_id":"10648aa3-b215-4c52-9577-5c5689a08939","event":"Loot","category":"loot","px":469.7,"py":218.4,"ts_relative":0,"is_bot":false},{"user_id":"10648aa3-b215-4c52-9577-5c5689a08939","event":"Position","category":"move_human","px":469.7,"py":218.4,"ts_relative":0,"is_bot":false},{"user_id":"10648aa3-b215-4c52-9577-5c5689a08939","event":"Loot","category":"loot","px":451.7,"py":218.2,"ts_relative":0,"is_bot":false},{"user_id":"10648aa3-b215-4c52-9577-5c5689a08939","event":"Position","category":"move_human","px":451.7,"py":218.2,"ts_relative":0,"is_bot":false},{"user_id":"10648aa3-b215-4c52-9577-5c5689a08939","event":"Position","category":"move_human","px":459.7,"py":237.4,"ts_relative":0,"is_bot":false},{"user_id":"10648aa3-b215-4c52-9577-5c5689a08939","event":"Position","category":"move_human","px":469.6,"py":256.4,"ts_relative":0,"is_bot":false},{"user_id":"10648aa3-b215-4c52-9577-5c5689a08939","event":"Position","category":"move_human","px":460.2,"py":280.9,"ts_relative":0,"is_bot":false},{"user_id":"10648aa3-b215-4c52-9577-5c5689a08939","event":"Position","category":"move_human","px":469.8,"py":316.4,"ts_relative":0,"is_bot":false},{"user_id":"10648aa3-b215-4c52-9577-5c5689a08939","event":"Position","category":"move_human","px":485.5,"py":349.1,"ts_relative":0,"is_bot":false},{"user_id":"10648aa3-b215-4c52-9577-5c5689a08939","event":"Position","category":"move_human","px":498.7,"py":376.4,"ts_relative":0,"is_bot":false},{"user_id":"10648aa3-b215-4c52-9577-5c5689a08939","event":"Position","category":"move_human","px":503.2,"py":408.5,"ts_relative":0,"is_bot":false},{"user_id":"10648aa3-b215-4c52-9577-5c5689a08939","event":"Position","category":"move_human","px":508.8,"py":431.8,"ts_relative":0,"is_bot":false},{"user_id":"10648aa3-b215-4c52-9577-5c5689a08939","event":"Position","category":"move_human","px":516.5,"py":457.3,"ts_relative":0,"is_bot":false},{"user_id":"10648aa3-b215-4c52-9577-5c5689a08939","event":"Position","category":"move_human","px":526.9,"py":478.3,"ts_relative":0,"is_bot":false},{"user_id":"10648aa3-b215-4c52-9577-5c5689a08939","event":"Position","category":"move_human","px":531.7,"py":494.2,"ts_relative":0,"is_bot":false},{"user_id":"10648aa3-b215-4c52-9577-5c5689a08939","event":"Loot","category":"loot","px":531.7,"py":494.2,"ts_relative":0,"is_bot":false},{"user_id":"10648aa3-b215-4c52-9577-5c5689a08939","event":"Loot","category":"loot","px":531.7,"py":494.2,"ts_relative":0,"is_bot":false},{"user_id":"10648aa3-b215-4c52-9577-5c5689a08939","event":"Position","category":"move_human","px":542.7,"py":509.4,"ts_relative":0,"is_bot":false},{"user_id":"10648aa3-b215-4c52-9577-5c5689a08939","event":"Position","category":"move_human","px":561.2,"py":539.7,"ts_relative":0,"is_bot":false},{"user_id":"10648aa3-b215-4c52-9577-5c5689a08939","event":"Position","category":"move_human","px":541.0,"py":545.8,"ts_relative":0,"is_bot":false},{"user_id":"10648aa3-b215-4c52-9577-5c5689a08939","event":"Position","category":"move_human","px":536.2,"py":562.8,"ts_relative":0,"is_bot":false},{"user_id":"10648aa3-b215-4c52-9577-5c5689a08939","event":"Loot","category":"loot","px":519.3,"py":571.1,"ts_relative":0,"is_bot":false},{"user_id":"10648aa3-b215-4c52-9577-5c5689a08939","event":"Position","category":"move_human","px":525.3,"py":570.4,"ts_relative":0,"is_bot":false},{"user_id":"10648aa3-b215-4c52-9577-5c5689a08939","event":"Position","category":"move_human","px":556.1,"py":565.9,"ts_relative":0,"is_bot":false},{"user_id":"10648aa3-b215-4c52-9577-5c5689a08939","event":"Position","category":"move_human","px":574.3,"py":585.4,"ts_relative":0,"is_bot":false},{"user_id":"10648aa3-b215-4c52-9577-5c5689a08939","event":"Position","category":"move_human","px":561.3,"py":592.6,"ts_relative":0,"is_bot":false},{"user_id":"10648aa3-b215-4c52-9577-5c5689a08939","event":"Position","category":"move_human","px":574.1,"py":597.4,"ts_relative":0,"is_bot":false},{"user_id":"10648aa3-b215-4c52-9577-5c5689a08939","event":"Position","category":"move_human","px":579.1,"py":596.2,"ts_relative":0,"is_bot":false},{"user_id":"10648aa3-b215-4c52-9577-5c5689a08939","event":"BotKilled","category":"combat","px":579.6,"py":595.8,"ts_relative":0,"is_bot":false}]}