{"match_id":"2cc08f74-2c06-4f08-92b5-abfcab7291ca.nakama-0","map_id":"GrandRift","duration_ms":0,"players":[{"user_id":"1379","is_bot":true,"events":20},{"user_id":"1382","is_bot":true,"events":32},{"user_id":"1385","is_bot":true,"events":33},{"user_id":"1396","is_bot":true,"events":31},{"user_id":"1400","is_bot":true,"events":31},{"user_id":"1403","is_bot":true,"events":24},{"user_id":"1406","is_bot":true,"events":30},{"user_id":"1410","is_bot":true,"events":25},{"user_id":"1413","is_bot":true,"events":32},{"user_id":"1416","is_bot":true,"events":31},{"user_id":"1420","is_bot":true,"events":32},{"user_id":"1423","is_bot":true,"events":32}],"events":[{"user_id":"1379","event":"Position","category":"move_human","px":115.8,"py":447.8,"ts_relative":0,"is_bot":true},{"user_id":"1379","event":"Position","category":"move_human","px":135.2,"py":471.2,"ts_relative":0,"is_bot":true},{"user_id":"1379","event":"Position","category":"move_human","px":166.1,"py":458.3,"ts_relative":0,"is_bot":true},{"user_id":"1379","event":"Position","category":"move_human","px":199.8,"py":474.1,"ts_relative":0,"is_bot":true},{"user_id":"1379","event":"Position","category":"move_human","px":210.2,"py":469.1,"ts_relative":0,"is_bot":true},{"user_id":"1379","event":"Loot","category":"loot","px":209.6,"py":473.5,"ts_relative":0,"is_bot":true},{"user_id":"1379","event":"Position","category":"move_human","px":212.5,"py":461.6,"ts_relative":0,"is_bot":true},{"user_id":"1379","event":"Position","category":"move_human","px":242.2,"py":429.6,"ts_relative":0,"is_bot":true},{"user_id":"1379","event":"Position","category":"move_human","px":276.8,"py":406.6,"ts_relative":0,"is_bot":true},{"user_id":"1379","event":"Position","category":"move_human","px":276.2,"py":396.0,"ts_relative":0,"is_bot":true},{"user_id":"1379","event":"Position","category":"move_human","px":254.1,"py":384.3,"ts_relative":0,"is_bot":true},{"user_id":"1379","event":"Loot","category":"loot","px":253.9,"py":384.0,"ts_relative":0,"is_bot":true},{"user_id":"1379","event":"Loot","category":"loot","px":253.9,"py":384.0,"ts_relative":0,"is_bot":true},{"user_id":"1379","event":"Position","category":"move_human","px":219.9,"py":409.5,"ts_relative":0,"is_bot":true},{"user_id":"1379","event":"Position","category":"move_human","px":212.8,"py":427.9,"ts_relative":0,"is_bot":true},{"user_id":"1379","event":"Position","category":"move_human","px":251.7,"py":412.3,"ts_relative":0,"is_bot":true},{"user_id":"1379","event":"Position","category":"move_human","px":222.6,"py":377.4,"ts_relative":0,"is_bot":true},{"user_id":"1379","event":"Position","category":"move_human","px":213.7,"py":363.9,"ts_relative":0,"is_bot":true},{"user_id":"1379","event":"Position","category":"move_human","px":220.2,"py":372.3,"ts_relative":0,"is_bot":true},{"user_id":"1379","event":"Position","category":"move_human","px":252.0,"py":358.3,"ts_relative":0,"is_bot":true},{"user_id":"1382","event":"BotPosition","category":"move_bot","px":133.1,"py":470.2,"ts_relative":0,"is_bot":true},{"user_id":"1382","event":"BotPosition","category":"move_bot","px":134.6,"py":463.1,"ts_relative":0,"is_bot":true},{"user_id":"1382","event":"BotPosition","category":"move_bot","px":146.0,"py":450.6,"ts_relative":0,"is_bot":true},{"user_id":"1382","event":"BotPosition","category":"move_bot","px":162.9,"py":453.6,"ts_relative":0,"is_bot":true},{"user_id":"1382","event":"BotPosition","category":"move_bot","px":194.7,"py":479.6,"ts_relative":0,"is_bot":true},{"user_id":"1382","event":"BotPosition","category":"move_bot","px":223.1,"py":491.2,"ts_relative":0,"is_bot":true},{"user_id":"1382","event":"BotPosition","category":"move_bot","px":219.1,"py":484.2,"ts_relative":0,"is_bot":true},{"user_id":"1382","event":"BotPosition","category":"move_bot","px":207.7,"py":467.4,"ts_relative":0,"is_bot":true},{"user_id":"1382","event":"BotPosition","category":"move_bot","px":193.1,"py":442.1,"ts_relative":0,"is_bot":true},{"user_id":"1382","event":"BotPosition","category":"move_bot","px":205.7,"py":428.9,"ts_relative":0,"is_bot":true},{"user_id":"1382","event":"BotPosition","category":"move_bot","px":213.3,"py":386.5,"ts_relative":0,"is_bot":true},{"user_id":"1382","event":"BotPosition","category":"move_bot","px":250.9,"py":398.5,"ts_relative":0,"is_bot":true},{"user_id":"1382","event":"BotPosition","category":"move_bot","px":221.8,"py":412.6,"ts_relative":0,"is_bot":true},{"user_id":"1382","event":"BotPosition","category":"move_bot","px":250.9,"py":415.0,"ts_relative":0,"is_bot":true},{"user_id":"1382","event":"BotPosition","category":"move_bot","px":255.8,"py":426.5,"ts_relative":0,"is_bot":true},{"user_id":"1382","event":"BotPosition","category":"move_bot","px":233.8,"py":394.1,"ts_relative":0,"is_bot":true},{"user_id":"1382","event":"BotPosition","category":"move_bot","px":257.7,"py":418.0,"ts_relative":0,"is_bot":true},{"user_id":"1382","event":"BotPosition","category":"move_bot","px":237.2,"py":389.6,"ts_relative":0,"is_bot":true},{"user_id":"1382","event":"BotPosition","category":"move_bot","px":218.4,"py":363.1,"ts_relative":0,"is_bot":true},{"user_id":"1382","event":"BotPosition","category":"move_bot","px":249.4,"py":364.4,"ts_relative":0,"is_bot":true},{"user_id":"1382","event":"BotPosition","category":"move_bot","px":267.2,"py":365.5,"ts_relative":0,"is_bot":true},{"user_id":"1382","event":"BotPosition","category":"move_bot","px":248.9,"py":385.9,"ts_relative":0,"is_bot":true},{"user_id":"1382","event":"BotPosition","category":"move_bot","px":233.7,"py":410.7,"ts_relative":0,"is_bot":true},{"user_id":"1382","event":"BotPosition","category":"move_bot","px":246.8,"py":383.6,"ts_relative":0,"is_bot":true},{"user_id":"1382","event":"BotPosition","category":"move_bot","px":249.3,"py":361.3,"ts_relative":0,"is_bot":true},{"user_id":"1382","event":"BotPosition","category":"move_bot","px":265.7,"py":351.8,"ts_relative":0,"is_bot":true},{"user_id":"1382","event":"BotPosition","category":"move_bot","px":275.3,"py":364.5,"ts_relative":0,"is_bot":true},{"user_id":"1382","event":"BotPosition","category":"move_bot","px":301.1,"py":376.6,"ts_relative":0,"is_bot":true},{"user_id":"1382","event":"BotPosition","category":"move_bot","px":330.6,"py":358.7,"ts_relative":0,"is_bot":true},{"user_id":"1382","event":"BotPosition","category":"move_bot","px":372.5,"py":351.5,"ts_relative":0,"is_bot":true},{"user_id":"1382","event":"BotPosition","category":"move_bot","px":414.1,"py":358.5,"ts_relative":0,"is_bot":true},{"user_id":"1382","event":"BotPosition","category":"move_bot","px":424.3,"py":399.1,"ts_relative":0,"is_bot":true},{"user_id":"1385","event":"BotPosition","category":"move_bot","px":150.3,"py":449.0,"ts_relative":0,"is_bot":true},{"user_id":"1385","event":"BotPosition","category":"move_bot","px":133.6,"py":466.5,"ts_relative":0,"is_bot":true},{"user_id":"1385","event":"BotPosition","category":"move_bot","px":136.2,"py":478.7,"ts_relative":0,"is_bot":true},{"user_id":"1385","event":"BotPosition","category":"move_bot","px":148.7,"py":456.7,"ts_relative":0,"is_bot":true},{"user_id":"1385","event":"BotPosition","category":"move_bot","px":191.9,"py":455.8,"ts_relative":0,"is_bot":true},{"user_id":"1385","event":"BotPosition","category":"move_bot","px":214.4,"py":459.9,"ts_relative":0,"is_bot":true},{"user_id":"1385","event":"BotPosition","category":"move_bot","px":178.4,"py":459.9,"ts_relative":0,"is_bot":true},{"user_id":"1385","event":"BotPosition","category":"move_bot","px":196.9,"py":453.1,"ts_relative":0,"is_bot":true},{"user_id":"1385","event":"BotPosition","category":"move_bot","px":220.5,"py":441.2,"ts_relative":0,"is_bot":true},{"user_id":"1385","event":"BotPosition","category":"move_bot","px":258.8,"py":439.4,"ts_relative":0,"is_bot":true},{"user_id":"1385","event":"BotPosition","category":"move_bot","px":276.4,"py":416.1,"ts_relative":0,"is_bot":true},{"user_id":"1385","event":"BotPosition","category":"move_bot","px":257.2,"py":403.5,"ts_relative":0,"is_bot":true},{"user_id":"1385","event":"BotPosition","category":"move_bot","px":220.2,"py":387.8,"ts_relative":0,"is_bot":true},{"user_id":"1385","event":"BotPosition","category":"move_bot","px":229.0,"py":390.7,"ts_relative":0,"is_bot":true},{"user_id":"1385","event":"BotPosition","category":"move_bot","px":265.6,"py":402.8,"ts_relative":0,"is_bot":true},{"user_id":"1385","event":"BotPosition","category":"move_bot","px":254.4,"py":401.6,"ts_relative":0,"is_bot":true},{"user_id":"1385","event":"BotPosition","category":"move_bot","px":216.2,"py":416.3,"ts_relative":0,"is_bot":true},{"user_id":"1385","event":"BotPosition","category":"move_bot","px":227.9,"py":417.9,"ts_relative":0,"is_bot":true},{"user_id":"1385","event":"BotPosition","category":"move_bot","px":254.6,"py":423.4,"ts_relative":0,"is_bot":true},{"user_id":"1385","event":"BotPosition","category":"move_bot","px":233.4,"py":397.9,"ts_relative":0,"is_bot":true},{"user_id":"1385","event":"BotPosition","category":"move_bot","px":208.3,"py":391.2,"ts_relative":0,"is_bot":true},{"user_id":"1385","event":"BotPosition","category":"move_bot","px":225.6,"py":391.7,"ts_relative":0,"is_bot":true},{"user_id":"1385","event":"BotPosition","category":"move_bot","px":246.6,"py":382.1,"ts_relative":0,"is_bot":true},{"user_id":"1385","event":"BotPosition","category":"move_bot","px":275.7,"py":369.8,"ts_relative":0,"is_bot":true},{"user_id":"1385","event":"BotPosition","category":"move_bot","px":241.8,"py":390.0,"ts_relative":0,"is_bot":true},{"user_id":"1385","event":"BotPosition","category":"move_bot","px":232.8,"py":397.7,"ts_relative":0,"is_bot":true},{"user_id":"1385","event":"BotPosition","category":"move_bot","px":229.6,"py":387.4,"ts_relative":0,"is_bot":true},{"user_id":"1385","event":"BotPosition","category":"move_bot","px":257.7,"py":355.1,"ts_relative":0,"is_bot":true},{"user_id":"1385","event":"BotPosition","category":"move_bot","px":269.4,"py":360.0,"ts_relative":0,"is_bot":true},{"user_id":"1385","event":"BotPosition","category":"move_bot","px":269.7,"py":352.9,"ts_relative":0,"is_bot":true},{"user_id":"1385","event":"BotPosition","category":"move_bot","px":301.9,"py":352.9,"ts_relative":0,"is_bot":true},{"user_id":"1385","event":"BotPosition","category":"move_bot","px":331.7,"py":355.2,"ts_relative":0,"is_bot":true},{"user_id":"1385","event":"BotPosition","category":"move_bot","px":371.4,"py":351.6,"ts_relative":0,"is_bot":true},{"user_id":"1396","event":"BotPosition","category":"move_bot","px":916.7,"py":609.5,"ts_relative":0,"is_bot":true},{"user_id":"1396","event":"BotPosition","category":"move_bot","px":907.2,"py":595.1,"ts_relative":0,"is_bot":true},{"user_id":"1396","event":"BotPosition","category":"move_bot","px":891.0,"py":615.3,"ts_relative":0,"is_bot":true},{"user_id":"1396","event":"BotPosition","category":"move_bot","px":853.3,"py":616.5,"ts_relative":0,"is_bot":true},{"user_id":"1396","event":"BotPosition","category":"move_bot","px":814.7,"py":618.1,"ts_relative":0,"is_bot":true},{"user_id":"1396","event":"BotPosition","category":"move_bot","px":782.8,"py":619.6,"ts_relative":0,"is_bot":true},{"user_id":"1396","event":"BotPosition","category":"move_bot","px":740.4,"py":611.0,"ts_relative":0,"is_bot":true},{"user_id":"1396","event":"BotPosition","category":"move_bot","px":697.8,"py":605.2,"ts_relative":0,"is_bot":true},{"user_id":"1396","event":"BotPosition","category":"move_bot","px":655.2,"py":599.4,"ts_relative":0,"is_bot":true},{"user_id":"1396","event":"BotPosition","category":"move_bot","px":612.8,"py":593.7,"ts_relative":0,"is_bot":true},{"user_id":"1396","event":"BotPosition","category":"move_bot","px":572.1,"py":585.1,"ts_relative":0,"is_bot":true},{"user_id":"1396","event":"BotPosition","category":"move_bot","px":532.5,"py":571.0,"ts_relative":0,"is_bot":true},{"user_id":"1396","event":"BotPosition","category":"move_bot","px":523.7,"py":556.6,"ts_relative":0,"is_bot":true},{"user_id":"1396","event":"BotPosition","category":"move_bot","px":535.9,"py":574.8,"ts_relative":0,"is_bot":true},{"user_id":"1396","event":"BotPosition","category":"move_bot","px":525.2,"py":568.3,"ts_relative":0,"is_bot":true},{"user_id":"1396","event":"BotPosition","category":"move_bot","px":527.4,"py":556.2,"ts_relative":0,"is_bot":true},{"user_id":"1396","event":"BotPosition","category":"move_bot","px":520.8,"py":562.3,"ts_relative":0,"is_bot":true},{"user_id":"1396","event":"BotPosition","category":"move_bot","px":514.3,"py":562.4,"ts_relative":0,"is_bot":true},{"user_id":"1396","event":"BotPosition","category":"move_bot","px":481.0,"py":575.5,"ts_relative":0,"is_bot":true},{"user_id":"1396","event":"BotPosition","category":"move_bot","px":485.4,"py":564.6,"ts_relative":0,"is_bot":true},{"user_id":"1396","event":"BotPosition","category":"move_bot","px":496.3,"py":533.7,"ts_relative":0,"is_bot":true},{"user_id":"1396","event":"BotPosition","category":"move_bot","px":478.6,"py":568.5,"ts_relative":0,"is_bot":true},{"user_id":"1396","event":"BotPosition","category":"move_bot","px":495.3,"py":558.5,"ts_relative":0,"is_bot":true},{"user_id":"1396","event":"BotPosition","category":"move_bot","px":477.5,"py":569.8,"ts_relative":0,"is_bot":true},{"user_id":"1396","event":"BotPosition","category":"move_bot","px":485.5,"py":560.0,"ts_relative":0,"is_bot":true},{"user_id":"1396","event":"BotPosition","category":"move_bot","px":506.0,"py":556.9,"ts_relative":0,"is_bot":true},{"user_id":"1396","event":"BotPosition","category":"move_bot","px":496.8,"py":518.0,"ts_relative":0,"is_bot":true},{"user_id":"1396","event":"BotPosition","category":"move_bot","px":505.0,"py":492.9,"ts_relative":0,"is_bot":true},{"user_id":"1396","event":"BotPosition","category":"move_bot","px":502.2,"py":505.8,"ts_relative":0,"is_bot":true},{"user_id":"1396","event":"BotPosition","category":"move_bot","px":506.4,"py":500.4,"ts_relative":0,"is_bot":true},{"user_id":"1396","event":"BotPosition","category":"move_bot","px":507.8,"py":492.7,"ts_relative":0,"is_bot":true},{"user_id":"1400","event":"BotPosition","category":"move_bot","px":913.1,"py":584.7,"ts_relative":0,"is_bot":true},{"user_id":"1400","event":"BotPosition","category":"move_bot","px":881.7,"py":562.7,"ts_relative":0,"is_bot":true},{"user_id":"1400","event":"BotPosition","category":"move_bot","px":880.7,"py":595.2,"ts_relative":0,"is_bot":true},{"user_id":"1400","event":"BotPosition","category":"move_bot","px":853.9,"py":582.9,"ts_relative":0,"is_bot":true},{"user_id":"1400","event":"BotPosition","category":"move_bot","px":856.3,"py":587.8,"ts_relative":0,"is_bot":true},{"user_id":"1400","event":"BotPosition","category":"move_bot","px":859.1,"py":599.0,"ts_relative":0,"is_bot":true},{"user_id":"1400","event":"BotPosition","category":"move_bot","px":830.5,"py":599.0,"ts_relative":0,"is_bot":true},{"user_id":"1400","event":"BotPosition","category":"move_bot","px":795.4,"py":598.9,"ts_relative":0,"is_bot":true},{"user_id":"1400","event":"BotPosition","category":"move_bot","px":778.5,"py":604.1,"ts_relative":0,"is_bot":true},{"user_id":"1400","event":"BotPosition","category":"move_bot","px":737.0,"py":592.5,"ts_relative":0,"is_bot":true},{"user_id":"1400","event":"BotPosition","category":"move_bot","px":697.5,"py":581.6,"ts_relative":0,"is_bot":true},{"user_id":"1400","event":"BotPosition","category":"move_bot","px":656.6,"py":570.7,"ts_relative":0,"is_bot":true},{"user_id":"1400","event":"BotPosition","category":"move_bot","px":625.5,"py":572.2,"ts_relative":0,"is_bot":true},{"user_id":"1400","event":"BotPosition","category":"move_bot","px":588.5,"py":590.6,"ts_relative":0,"is_bot":true},{"user_id":"1400","event":"BotPosition","category":"move_bot","px":552.1,"py":575.6,"ts_relative":0,"is_bot":true},{"user_id":"1400","event":"BotPosition","category":"move_bot","px":533.6,"py":574.6,"ts_relative":0,"is_bot":true},{"user_id":"1400","event":"BotPosition","category":"move_bot","px":540.3,"py":574.5,"ts_relative":0,"is_bot":true},{"user_id":"1400","event":"BotPosition","category":"move_bot","px":534.1,"py":560.2,"ts_relative":0,"is_bot":true},{"user_id":"1400","event":"BotPosition","category":"move_bot","px":551.1,"py":567.0,"ts_relative":0,"is_bot":true},{"user_id":"1400","event":"BotPosition","category":"move_bot","px":518.8,"py":570.0,"ts_relative":0,"is_bot":true},{"user_id":"1400","event":"BotPosition","category":"move_bot","px":518.0,"py":557.4,"ts_relative":0,"is_bot":true},{"user_id":"1400","event":"BotPosition","category":"move_bot","px":517.7,"py":561.0,"ts_relative":0,"is_bot":true},{"user_id":"1400","event":"BotPosition","category":"move_bot","px":517.6,"py":542.1,"ts_relative":0,"is_bot":true},{"user_id":"1400","event":"BotPosition","category":"move_bot","px":517.6,"py":559.3,"ts_relative":0,"is_bot":true},{"user_id":"1400","event":"BotPosition","category":"move_bot","px":525.8,"py":554.1,"ts_relative":0,"is_bot":true},{"user_id":"1400","event":"BotPosition","category":"move_bot","px":510.1,"py":561.3,"ts_relative":0,"is_bot":true},{"user_id":"1400","event":"BotPosition","category":"move_bot","px":502.3,"py":568.2,"ts_relative":0,"is_bot":true},{"user_id":"1400","event":"BotPosition","category":"move_bot","px":486.1,"py":576.5,"ts_relative":0,"is_bot":true},{"user_id":"1400","event":"BotPosition","category":"move_bot","px":480.4,"py":575.8,"ts_relative":0,"is_bot":true},{"user_id":"1400","event":"BotPosition","category":"move_bot","px":510.1,"py":562.1,"ts_relative":0,"is_bot":true},{"user_id":"1400","event":"BotPosition","category":"move_bot","px":477.1,"py":564.1,"ts_relative":0,"is_bot":true},{"user_id":"1403","event":"BotPosition","category":"move_bot","px":926.0,"py":602.6,"ts_relative":0,"is_bot":true},{"user_id":"1403","event":"BotPosition","category":"move_bot","px":885.9,"py":615.2,"ts_relative":0,"is_bot":true},{"user_id":"1403","event":"BotPosition","category":"move_bot","px":870.1,"py":616.7,"ts_relative":0,"is_bot":true},{"user_id":"1403","event":"BotPosition","category":"move_bot","px":849.7,"py":596.3,"ts_relative":0,"is_bot":true},{"user_id":"1403","event":"BotPosition","category":"move_bot","px":842.3,"py":568.0,"ts_relative":0,"is_bot":true},{"user_id":"1403","event":"BotPosition","category":"move_bot","px":853.6,"py":601.5,"ts_relative":0,"is_bot":true},{"user_id":"1403","event":"BotPosition","category":"move_bot","px":825.9,"py":592.1,"ts_relative":0,"is_bot":true},{"user_id":"1403","event":"BotPosition","category":"move_bot","px":784.9,"py":581.9,"ts_relative":0,"is_bot":true},{"user_id":"1403","event":"BotPosition","category":"move_bot","px":761.1,"py":610.0,"ts_relative":0,"is_bot":true},{"user_id":"1403","event":"BotPosition","category":"move_bot","px":727.7,"py":595.8,"ts_relative":0,"is_bot":true},{"user_id":"1403","event":"BotPosition","category":"move_bot","px":696.2,"py":584.3,"ts_relative":0,"is_bot":true},{"user_id":"1403","event":"BotPosition","category":"move_bot","px":659.2,"py":572.3,"ts_relative":0,"is_bot":true},{"user_id":"1403","event":"BotPosition","category":"move_bot","px":635.6,"py":575.8,"ts_relative":0,"is_bot":true},{"user_id":"1403","event":"BotPosition","category":"move_bot","px":595.4,"py":589.4,"ts_relative":0,"is_bot":true},{"user_id":"1403","event":"BotPosition","category":"move_bot","px":560.6,"py":579.3,"ts_relative":0,"is_bot":true},{"user_id":"1403","event":"BotPosition","category":"move_bot","px":525.7,"py":585.6,"ts_relative":0,"is_bot":true},{"user_id":"1403","event":"BotKill","category":"combat","px":525.7,"py":585.7,"ts_relative":0,"is_bot":true},{"user_id":"1403","event":"BotPosition","category":"move_bot","px":501.8,"py":610.5,"ts_relative":0,"is_bot":true},{"user_id":"1403","event":"BotPosition","category":"move_bot","px":470.2,"py":624.1,"ts_relative":0,"is_bot":true},{"user_id":"1403","event":"BotKill","category":"combat","px":469.9,"py":624.2,"ts_relative":0,"is_bot":true},{"user_id":"1403","event":"BotPosition","category":"move_bot","px":461.5,"py":642.5,"ts_relative":0,"is_bot":true},{"user_id":"1403","event":"BotKill","category":"combat","px":463.6,"py":638.3,"ts_relative":0,"is_bot":true},{"user_id":"1403","event":"BotPosition","category":"move_bot","px":466.5,"py":633.6,"ts_relative":0,"is_bot":true},{"user_id":"1403","event":"BotKilled","category":"combat","px":461.5,"py":632.3,"ts_relative":0,"is_bot":true},{"user_id":"1406","event":"BotPosition","category":"move_bot","px":350.2,"py":415.0,"ts_relative":0,"is_bot":true},{"user_id":"1406","event":"BotPosition","category":"move_bot","px":367.2,"py":426.8,"ts_relative":0,"is_bot":true},{"user_id":"1406","event":"BotPosition","category":"move_bot","px":372.5,"py":434.0,"ts_relative":0,"is_bot":true},{"user_id":"1406","event":"BotPosition","category":"move_bot","px":383.7,"py":438.2,"ts_relative":0,"is_bot":true},{"user_id":"1406","event":"BotPosition","category":"move_bot","px":413.8,"py":461.4,"ts_relative":0,"is_bot":true},{"user_id":"1406","event":"BotPosition","category":"move_bot","px":443.7,"py":489.0,"ts_relative":0,"is_bot":true},{"user_id":"1406","event":"BotPosition","category":"move_bot","px":448.8,"py":481.3,"ts_relative":0,"is_bot":true},{"user_id":"1406","event":"BotPosition","category":"move_bot","px":453.4,"py":507.7,"ts_relative":0,"is_bot":true},{"user_id":"1406","event":"BotPosition","category":"move_bot","px":463.1,"py":537.6,"ts_relative":0,"is_bot":true},{"user_id":"1406","event":"BotPosition","category":"move_bot","px":487.5,"py":534.1,"ts_relative":0,"is_bot":true},{"user_id":"1406","event":"BotPosition","category":"move_bot","px":493.6,"py":518.7,"ts_relative":0,"is_bot":true},{"user_id":"1406","event":"BotPosition","category":"move_bot","px":480.6,"py":560.0,"ts_relative":0,"is_bot":true},{"user_id":"1406","event":"BotPosition","category":"move_bot","px":448.1,"py":576.4,"ts_relative":0,"is_bot":true},{"user_id":"1406","event":"BotPosition","category":"move_bot","px":436.9,"py":600.9,"ts_relative":0,"is_bot":true},{"user_id":"1406","event":"BotPosition","category":"move_bot","px":453.0,"py":614.4,"ts_relative":0,"is_bot":true},{"user_id":"1406","event":"BotPosition","category":"move_bot","px":462.8,"py":578.9,"ts_relative":0,"is_bot":true},{"user_id":"1406","event":"BotPosition","category":"move_bot","px":488.2,"py":556.5,"ts_relative":0,"is_bot":true},{"user_id":"1406","event":"BotPosition","category":"move_bot","px":497.9,"py":517.8,"ts_relative":0,"is_bot":true},{"user_id":"1406","event":"BotPosition","category":"move_bot","px":493.8,"py":501.3,"ts_relative":0,"is_bot":true},{"user_id":"1406","event":"BotPosition","category":"move_bot","px":507.0,"py":496.9,"ts_relative":0,"is_bot":true},{"user_id":"1406","event":"BotPosition","category":"move_bot","px":508.4,"py":512.6,"ts_relative":0,"is_bot":true},{"user_id":"1406","event":"BotPosition","category":"move_bot","px":501.0,"py":514.2,"ts_relative":0,"is_bot":true},{"user_id":"1406","event":"BotPosition","category":"move_bot","px":499.2,"py":523.0,"ts_relative":0,"is_bot":true},{"user_id":"1406","event":"BotPosition","category":"move_bot","px":502.6,"py":543.8,"ts_relative":0,"is_bot":true},{"user_id":"1406","event":"BotPosition","category":"move_bot","px":509.1,"py":557.2,"ts_relative":0,"is_bot":true},{"user_id":"1406","event":"BotPosition","category":"move_bot","px":526.5,"py":550.6,"ts_relative":0,"is_bot":true},{"user_id":"1406","event":"BotPosition","category":"move_bot","px":517.1,"py":526.4,"ts_relative":0,"is_bot":true},{"user_id":"1406","event":"BotPosition","category":"move_bot","px":518.6,"py":539.3,"ts_relative":0,"is_bot":true},{"user_id":"1406","event":"BotPosition","category":"move_bot","px":518.0,"py":568.2,"ts_relative":0,"is_bot":true},{"user_id":"1406","event":"BotPosition","category":"move_bot","px":521.5,"py":544.4,"ts_relative":0,"is_bot":true},{"user_id":"1410","event":"BotPosition","category":"move_bot","px":325.6,"py":363.8,"ts_relative":0,"is_bot":true},{"user_id":"1410","event":"BotPosition","category":"move_bot","px":332.7,"py":393.6,"ts_relative":0,"is_bot":true},{"user_id":"1410","event":"BotPosition","category":"move_bot","px":354.8,"py":358.2,"ts_relative":0,"is_bot":true},{"user_id":"1410","event":"BotPosition","category":"move_bot","px":376.6,"py":361.0,"ts_relative":0,"is_bot":true},{"user_id":"1410","event":"BotPosition","category":"move_bot","px":381.6,"py":388.6,"ts_relative":0,"is_bot":true},{"user_id":"1410","event":"BotPosition","category":"move_bot","px":361.7,"py":354.9,"ts_relative":0,"is_bot":true},{"user_id":"1410","event":"BotPosition","category":"move_bot","px":347.5,"py":391.4,"ts_relative":0,"is_bot":true},{"user_id":"1410","event":"BotPosition","category":"move_bot","px":345.2,"py":431.0,"ts_relative":0,"is_bot":true},{"user_id":"1410","event":"BotPosition","category":"move_bot","px":374.5,"py":436.0,"ts_relative":0,"is_bot":true},{"user_id":"1410","event":"BotPosition","category":"move_bot","px":400.2,"py":436.2,"ts_relative":0,"is_bot":true},{"user_id":"1410","event":"BotPosition","category":"move_bot","px":414.7,"py":404.9,"ts_relative":0,"is_bot":true},{"user_id":"1410","event":"BotPosition","category":"move_bot","px":439.9,"py":386.3,"ts_relative":0,"is_bot":true},{"user_id":"1410","event":"BotPosition","category":"move_bot","px":464.4,"py":383.6,"ts_relative":0,"is_bot":true},{"user_id":"1410","event":"BotPosition","category":"move_bot","px":486.1,"py":383.0,"ts_relative":0,"is_bot":true},{"user_id":"1410","event":"BotPosition","category":"move_bot","px":510.4,"py":414.5,"ts_relative":0,"is_bot":true},{"user_id":"1410","event":"BotPosition","category":"move_bot","px":506.5,"py":439.8,"ts_relative":0,"is_bot":true},{"user_id":"1410","event":"BotPosition","category":"move_bot","px":509.5,"py":459.1,"ts_relative":0,"is_bot":true},{"user_id":"1410","event":"BotPosition","category":"move_bot","px":528.3,"py":486.5,"ts_relative":0,"is_bot":true},{"user_id":"1410","event":"BotPosition","category":"move_bot","px":525.1,"py":485.6,"ts_relative":0,"is_bot":true},{"user_id":"1410","event":"BotPosition","category":"move_bot","px":522.6,"py":506.2,"ts_relative":0,"is_bot":true},{"user_id":"1410","event":"BotPosition","category":"move_bot","px":521.4,"py":501.7,"ts_relative":0,"is_bot":true},{"user_id":"1410","event":"BotPosition","category":"move_bot","px":518.0,"py":471.7,"ts_relative":0,"is_bot":true},{"user_id":"1410","event":"BotPosition","category":"move_bot","px":519.7,"py":476.9,"ts_relative":0,"is_bot":true},{"user_id":"1410","event":"BotPosition","category":"move_bot","px":519.9,"py":473.5,"ts_relative":0,"is_bot":true},{"user_id":"1410","event":"BotKilled","category":"combat","px":518.6,"py":471.7,"ts_relative":0,"is_bot":true},{"user_id":"1413","event":"BotPosition","category":"move_bot","px":320.6,"py":415.1,"ts_relative":0,"is_bot":true},{"user_id":"1413","event":"BotPosition","category":"move_bot","px":361.1,"py":430.9,"ts_relative":0,"is_bot":true},{"user_id":"1413","event":"BotPosition","category":"move_bot","px":387.4,"py":442.0,"ts_relative":0,"is_bot":true},{"user_id":"1413","event":"BotPosition","category":"move_bot","px":381.4,"py":436.0,"ts_relative":0,"is_bot":true},{"user_id":"1413","event":"BotPosition","category":"move_bot","px":363.6,"py":416.1,"ts_relative":0,"is_bot":true},{"user_id":"1413","event":"BotPosition","category":"move_bot","px":352.1,"py":383.4,"ts_relative":0,"is_bot":true},{"user_id":"1413","event":"BotPosition","category":"move_bot","px":354.8,"py":362.0,"ts_relative":0,"is_bot":true},{"user_id":"1413","event":"BotPosition","category":"move_bot","px":373.2,"py":340.5,"ts_relative":0,"is_bot":true},{"user_id":"1413","event":"BotPosition","category":"move_bot","px":377.6,"py":378.8,"ts_relative":0,"is_bot":true},{"user_id":"1413","event":"BotPosition","category":"move_bot","px":401.2,"py":402.8,"ts_relative":0,"is_bot":true},{"user_id":"1413","event":"BotPosition","category":"move_bot","px":434.8,"py":410.1,"ts_relative":0,"is_bot":true},{"user_id":"1413","event":"BotPosition","category":"move_bot","px":471.5,"py":388.7,"ts_relative":0,"is_bot":true},{"user_id":"1413","event":"BotPosition","category":"move_bot","px":460.2,"py":387.2,"ts_relative":0,"is_bot":true},{"user_id":"1413","event":"BotPosition","category":"move_bot","px":462.1,"py":428.3,"ts_relative":0,"is_bot":true},{"user_id":"1413","event":"BotPosition","category":"move_bot","px":456.9,"py":443.6,"ts_relative":0,"is_bot":true},{"user_id":"1413","event":"BotPosition","category":"move_bot","px":459.7,"py":405.6,"ts_relative":0,"is_bot":true},{"user_id":"1413","event":"BotPosition","category":"move_bot","px":459.9,"py":420.6,"ts_relative":0,"is_bot":true},{"user_id":"1413","event":"BotPosition","category":"move_bot","px":459.9,"py":400.0,"ts_relative":0,"is_bot":true},{"user_id":"1413","event":"BotPosition","category":"move_bot","px":475.6,"py":378.6,"ts_relative":0,"is_bot":true},{"user_id":"1413","event":"BotPosition","category":"move_bot","px":486.1,"py":364.6,"ts_relative":0,"is_bot":true},{"user_id":"1413","event":"BotPosition","category":"move_bot","px":483.5,"py":369.5,"ts_relative":0,"is_bot":true},{"user_id":"1413","event":"BotPosition","category":"move_bot","px":489.4,"py":355.8,"ts_relative":0,"is_bot":true},{"user_id":"1413","event":"BotPosition","category":"move_bot","px":517.6,"py":347.0,"ts_relative":0,"is_bot":true},{"user_id":"1413","event":"BotPosition","category":"move_bot","px":526.5,"py":362.2,"ts_relative":0,"is_bot":true},{"user_id":"1413","event":"BotPosition","category":"move_bot","px":513.3,"py":402.6,"ts_relative":0,"is_bot":true},{"user_id":"1413","event":"BotKill","category":"combat","px":510.7,"py":417.6,"ts_relative":0,"is_bot":true},{"user_id":"1413","event":"BotPosition","category":"move_bot","px":512.7,"py":424.9,"ts_relative":0,"is_bot":true},{"user_id":"1413","event":"BotPosition","category":"move_bot","px":512.7,"py":418.2,"ts_relative":0,"is_bot":true},{"user_id":"1413","event":"BotPosition","category":"move_bot","px":510.5,"py":420.4,"ts_relative":0,"is_bot":true},{"user_id":"1413","event":"BotPosition","category":"move_bot","px":509.2,"py":459.8,"ts_relative":0,"is_bot":true},{"user_id":"1413","event":"BotPosition","category":"move_bot","px":509.3,"py":495.7,"ts_relative":0,"is_bot":true},{"user_id":"1413","event":"BotPosition","category":"move_bot","px":511.4,"py":520.4,"ts_relative":0,"is_bot":true},{"user_id":"1416","event":"BotPosition","category":"move_bot","px":353.6,"py":802.4,"ts_relative":0,"is_bot":true},{"user_id":"1416","event":"BotPosition","category":"move_bot","px":365.3,"py":783.8,"ts_relative":0,"is_bot":true},{"user_id":"1416","event":"BotPosition","category":"move_bot","px":373.6,"py":757.5,"ts_relative":0,"is_bot":true},{"user_id":"1416","event":"BotPosition","category":"move_bot","px":376.5,"py":727.7,"ts_relative":0,"is_bot":true},{"user_id":"1416","event":"BotPosition","category":"move_bot","px":369.2,"py":704.2,"ts_relative":0,"is_bot":true},{"user_id":"1416","event":"BotPosition","category":"move_bot","px":372.2,"py":686.7,"ts_relative":0,"is_bot":true},{"user_id":"1416","event":"BotPosition","category":"move_bot","px":391.9,"py":665.1,"ts_relative":0,"is_bot":true},{"user_id":"1416","event":"BotPosition","category":"move_bot","px":427.7,"py":692.9,"ts_relative":0,"is_bot":true},{"user_id":"1416","event":"BotPosition","category":"move_bot","px":439.1,"py":711.9,"ts_relative":0,"is_bot":true},{"user_id":"1416","event":"BotPosition","category":"move_bot","px":466.0,"py":719.2,"ts_relative":0,"is_bot":true},{"user_id":"1416","event":"BotPosition","category":"move_bot","px":469.8,"py":756.7,"ts_relative":0,"is_bot":true},{"user_id":"1416","event":"BotPosition","category":"move_bot","px":489.6,"py":774.6,"ts_relative":0,"is_bot":true},{"user_id":"1416","event":"BotPosition","category":"move_bot","px":492.8,"py":780.7,"ts_relative":0,"is_bot":true},{"user_id":"1416","event":"BotPosition","category":"move_bot","px":523.3,"py":779.7,"ts_relative":0,"is_bot":true},{"user_id":"1416","event":"BotPosition","category":"move_bot","px":513.1,"py":763.7,"ts_relative":0,"is_bot":true},{"user_id":"1416","event":"BotPosition","category":"move_bot","px":542.8,"py":769.6,"ts_relative":0,"is_bot":true},{"user_id":"1416","event":"BotPosition","category":"move_bot","px":568.8,"py":789.9,"ts_relative":0,"is_bot":true},{"user_id":"1416","event":"BotPosition","category":"move_bot","px":580.6,"py":804.7,"ts_relative":0,"is_bot":true},{"user_id":"1416","event":"BotPosition","category":"move_bot","px":614.0,"py":782.5,"ts_relative":0,"is_bot":true},{"user_id":"1416","event":"BotPosition","category":"move_bot","px":637.0,"py":770.3,"ts_relative":0,"is_bot":true},{"user_id":"1416","event":"BotPosition","category":"move_bot","px":664.8,"py":775.3,"ts_relative":0,"is_bot":true},{"user_id":"1416","event":"BotPosition","category":"move_bot","px":675.2,"py":754.5,"ts_relative":0,"is_bot":true},{"user_id":"1416","event":"BotPosition","category":"move_bot","px":680.6,"py":718.3,"ts_relative":0,"is_bot":true},{"user_id":"1416","event":"BotPosition","category":"move_bot","px":699.2,"py":685.5,"ts_relative":0,"is_bot":true},{"user_id":"1416","event":"BotPosition","category":"move_bot","px":726.0,"py":653.4,"ts_relative":0,"is_bot":true},{"user_id":"1416","event":"BotPosition","category":"move_bot","px":758.2,"py":625.4,"ts_relative":0,"is_bot":true},{"user_id":"1416","event":"BotPosition","category":"move_bot","px":791.7,"py":598.4,"ts_relative":0,"is_bot":true},{"user_id":"1416","event":"BotPosition","category":"move_bot","px":829.7,"py":587.0,"ts_relative":0,"is_bot":true},{"user_id":"1416","event":"BotPosition","category":"move_bot","px":801.6,"py":574.7,"ts_relative":0,"is_bot":true},{"user_id":"1416","event":"BotPosition","category":"move_bot","px":785.8,"py":534.9,"ts_relative":0,"is_bot":true},{"user_id":"1416","event":"BotPosition","category":"move_bot","px":760.1,"py":504.7,"ts_relative":0,"is_bot":true},{"user_id":"1420","event":"BotPosition","category":"move_bot","px":383.7,"py":811.3,"ts_relative":0,"is_bot":true},{"user_id":"1420","event":"BotPosition","category":"move_bot","px":373.1,"py":797.8,"ts_relative":0,"is_bot":true},{"user_id":"1420","event":"BotPosition","category":"move_bot","px":354.9,"py":778.9,"ts_relative":0,"is_bot":true},{"user_id":"1420","event":"BotPosition","category":"move_bot","px":375.3,"py":763.4,"ts_relative":0,"is_bot":true},{"user_id":"1420","event":"BotPosition","category":"move_bot","px":367.9,"py":740.0,"ts_relative":0,"is_bot":true},{"user_id":"1420","event":"BotPosition","category":"move_bot","px":365.4,"py":710.2,"ts_relative":0,"is_bot":true},{"user_id":"1420","event":"BotPosition","category":"move_bot","px":388.3,"py":707.9,"ts_relative":0,"is_bot":true},{"user_id":"1420","event":"BotPosition","category":"move_bot","px":378.5,"py":667.1,"ts_relative":0,"is_bot":true},{"user_id":"1420","event":"BotPosition","category":"move_bot","px":400.2,"py":680.5,"ts_relative":0,"is_bot":true},{"user_id":"1420","event":"BotPosition","category":"move_bot","px":420.2,"py":689.7,"ts_relative":0,"is_bot":true},{"user_id":"1420","event":"BotPosition","category":"move_bot","px":453.7,"py":692.8,"ts_relative":0,"is_bot":true},{"user_id":"1420","event":"BotPosition","category":"move_bot","px":486.3,"py":717.9,"ts_relative":0,"is_bot":true},{"user_id":"1420","event":"BotPosition","category":"move_bot","px":463.0,"py":731.5,"ts_relative":0,"is_bot":true},{"user_id":"1420","event":"BotPosition","category":"move_bot","px":479.4,"py":765.5,"ts_relative":0,"is_bot":true},{"user_id":"1420","event":"BotPosition","category":"move_bot","px":507.8,"py":790.4,"ts_relative":0,"is_bot":true},{"user_id":"1420","event":"BotPosition","category":"move_bot","px":509.2,"py":796.5,"ts_relative":0,"is_bot":true},{"user_id":"1420","event":"BotPosition","category":"move_bot","px":533.3,"py":783.1,"ts_relative":0,"is_bot":true},{"user_id":"1420","event":"BotPosition","category":"move_bot","px":573.7,"py":783.6,"ts_relative":0,"is_bot":true},{"user_id":"1420","event":"BotPosition","category":"move_bot","px":582.8,"py":767.2,"ts_relative":0,"is_bot":true},{"user_id":"1420","event":"BotPosition","category":"move_bot","px":585.2,"py":792.8,"ts_relative":0,"is_bot":true},{"user_id":"1420","event":"BotPosition","category":"move_bot","px":579.1,"py":783.0,"ts_relative":0,"is_bot":true},{"user_id":"1420","event":"BotPosition","category":"move_bot","px":612.6,"py":764.9,"ts_relative":0,"is_bot":true},{"user_id":"1420","event":"BotPosition","category":"move_bot","px":636.6,"py":770.0,"ts_relative":0,"is_bot":true},{"user_id":"1420","event":"BotPosition","category":"move_bot","px":659.4,"py":749.6,"ts_relative":0,"is_bot":true},{"user_id":"1420","event":"BotPosition","category":"move_bot","px":667.4,"py":729.0,"ts_relative":0,"is_bot":true},{"user_id":"1420","event":"BotPosition","category":"move_bot","px":685.7,"py":712.2,"ts_relative":0,"is_bot":true},{"user_id":"1420","event":"BotPosition","category":"move_bot","px":705.6,"py":679.9,"ts_relative":0,"is_bot":true},{"user_id":"1420","event":"BotPosition","category":"move_bot","px":720.6,"py":650.6,"ts_relative":0,"is_bot":true},{"user_id":"1420","event":"BotPosition","category":"move_bot","px":754.8,"py":626.0,"ts_relative":0,"is_bot":true},{"user_id":"1420","event":"BotPosition","category":"move_bot","px":786.0,"py":601.9,"ts_relative":0,"is_bot":true},{"user_id":"1420","event":"BotPosition","category":"move_bot","px":802.8,"py":589.2,"ts_relative":0,"is_bot":true},{"user_id":"1420","event":"BotPosition","category":"move_bot","px":795.0,"py":548.2,"ts_relative":0,"is_bot":true},{"user_id":"1423","event":"BotPosition","category":"move_bot","px":367.8,"py":798.3,"ts_relative":0,"is_bot":true},{"user_id":"1423","event":"BotPosition","category":"move_bot","px":374.5,"py":755.9,"ts_relative":0,"is_bot":true},{"user_id":"1423","event":"BotPosition","category":"move_bot","px":394.3,"py":742.0,"ts_relative":0,"is_bot":true},{"user_id":"1423","event":"BotPosition","category":"move_bot","px":374.5,"py":771.2,"ts_relative":0,"is_bot":true},{"user_id":"1423","event":"BotPosition","category":"move_bot","px":369.2,"py":768.9,"ts_relative":0,"is_bot":true},{"user_id":"1423","event":"BotPosition","category":"move_bot","px":350.7,"py":773.7,"ts_relative":0,"is_bot":true},{"user_id":"1423","event":"BotPosition","category":"move_bot","px":338.1,"py":746.5,"ts_relative":0,"is_bot":true},{"user_id":"1423","event":"BotPosition","category":"move_bot","px":366.3,"py":720.8,"ts_relative":0,"is_bot":true},{"user_id":"1423","event":"BotPosition","category":"move_bot","px":375.3,"py":698.5,"ts_relative":0,"is_bot":true},{"user_id":"1423","event":"BotPosition","category":"move_bot","px":384.3,"py":676.6,"ts_relative":0,"is_bot":true},{"user_id":"1423","event":"BotPosition","category":"move_bot","px":416.0,"py":692.2,"ts_relative":0,"is_bot":true},{"user_id":"1423","event":"BotPosition","category":"move_bot","px":438.6,"py":716.2,"ts_relative":0,"is_bot":true},{"user_id":"1423","event":"BotPosition","category":"move_bot","px":452.2,"py":734.3,"ts_relative":0,"is_bot":true},{"user_id":"1423","event":"BotPosition","category":"move_bot","px":463.2,"py":776.3,"ts_relative":0,"is_bot":true},{"user_id":"1423","event":"BotPosition","category":"move_bot","px":479.9,"py":790.7,"ts_relative":0,"is_bot":true},{"user_id":"1423","event":"BotPosition","category":"move_bot","px":496.6,"py":771.9,"ts_relative":0,"is_bot":true},{"user_id":"1423","event":"BotPosition","category":"move_bot","px":522.3,"py":753.9,"ts_relative":0,"is_bot":true},{"user_id":"1423","event":"BotPosition","category":"move_bot","px":520.0,"py":778.9,"ts_relative":0,"is_bot":true},{"user_id":"1423","event":"BotPosition","category":"move_bot","px":544.6,"py":777.6,"ts_relative":0,"is_bot":true},{"user_id":"1423","event":"BotPosition","category":"move_bot","px":573.0,"py":789.0,"ts_relative":0,"is_bot":true},{"user_id":"1423","event":"BotPosition","category":"move_bot","px":595.6,"py":795.1,"ts_relative":0,"is_bot":true},{"user_id":"1423","event":"BotPosition","category":"move_bot","px":623.9,"py":772.0,"ts_relative":0,"is_bot":true},{"user_id":"1423","event":"BotPosition","category":"move_bot","px":636.2,"py":781.2,"ts_relative":0,"is_bot":true},{"user_id":"1423","event":"BotPosition","category":"move_bot","px":653.4,"py":764.9,"ts_relative":0,"is_bot":true},{"user_id":"1423","event":"BotPosition","category":"move_bot","px":664.0,"py":739.2,"ts_relative":0,"is_bot":true},{"user_id":"1423","event":"BotPosition","category":"move_bot","px":679.1,"py":712.3,"ts_relative":0,"is_bot":true},{"user_id":"1423","event":"BotPosition","category":"move_bot","px":704.9,"py":686.2,"ts_relative":0,"is_bot":true},{"user_id":"1423","event":"BotPosition","category":"move_bot","px":719.5,"py":660.2,"ts_relative":0,"is_bot":true},{"user_id":"1423","event":"BotPosition","category":"move_bot","px":748.5,"py":648.0,"ts_relative":0,"is_bot":true},{"user_id":"1423","event":"BotPosition","category":"move_bot","px":768.9,"py":622.7,"ts_relative":0,"is_bot":true},{"user_id":"1423","event":"BotPosition","category":"move_bot","px":799.9,"py":593.5,"ts_relative":0,"is_bot":true},{"user_id":"1423","event":"BotPosition","category":"move_bot","px":815.0,"py":581.9,"ts_relative":0,"is_bot":true}]}