{"match_id":"525deef0-21fb-4f5d-a590-732dda137bdb.nakama-0","map_id":"AmbroseValley","duration_ms":0,"players":[{"user_id":"a58b4a5f-0add-43fe-b986-1cea83120c5a","is_bot":false,"events":66}],"events":[{"user_id":"a58b4a5f-0add-43fe-b986-1cea83120c5a","event":"Position","category":"move_human","px":78.7,"py":890.2,"ts_relative":0,"is_bot":false},{"user_id":"a58b4a5f-0add-43fe-b986-1cea83120c5a","event":"Position","category":"move_human","px":84.8,"py":886.3,"ts_relative":0,"is_bot":false},{"user_id":"a58b4a5f-0add-43fe-b986-1cea83120c5a","event":"Position","category":"move_human","px":104.9,"py":877.7,"ts_relative":0,"is_bot":false},{"user_id":"a58b4a5f-0add-43fe-b986-1cea83120c5a","event":"Position","category":"move_human","px":130.3,"py":870.3,"ts_relative":0,"is_bot":false},{"user_id":"a58b4a5f-0add-43fe-b986-1cea83120c5a","event":"Position","category":"move_human","px":152.4,"py":856.8,"ts_relative":0,"is_bot":false},{"user_id":"a58b4a5f-0add-43fe-b986-1cea83120c5a","event":"Loot","category":"loot","px":162.7,"py":859.9,"ts_relative":0,"is_bot":false},{"user_id":"a58b4a5f-0add-43fe-b986-1cea83120c5a","event":"Position","category":"move_human","px":159.4,"py":861.8,"ts_relative":0,"is_bot":false},{"user_id":"a58b4a5f-0add-43fe-b986-1cea83120c5a","event":"Position","category":"move_human","px":166.5,"py":884.4,"ts_relative":0,"is_bot":false},{"user_id":"a58b4a5f-0add-43fe-b986-1cea83120c5a","event":"Loot","category":"loot","px":174.3,"py":876.3,"ts_relative":0,"is_bot":false},{"user_id":"a58b4a5f-0add-43fe-b986-1cea83120c5a","event":"Position","category":"move_human","px":166.5,"py":874.4,"ts_relative":0,"is_bot":false},{"user_id":"a58b4a5f-0add-43fe-b986-1cea83120c5a","event":"Position","category":"move_human","px":166.5,"py":864.8,"ts_relative":0,"is_bot":false},{"user_id":"a58b4a5f-0add-43fe-b986-1cea83120c5a","event":"Position","category":"move_human","px":161.1,"py":863.5,"ts_relative":0,"is_bot":false},{"user_id":"a58b4a5f-0add-43fe-b986-1cea83120c5a","event":"Loot","category":"loot","px":161.1,"py":863.5,"ts_relative":0,"is_bot":false},{"user_id":"a58b4a5f-0add-43fe-b986-1cea83120c5a","event":"Loot","category":"loot","px":161.1,"py":863.5,"ts_relative":0,"is_bot":false},{"user_id":"a58b4a5f-0add-43fe-b986-1cea83120c5a","event":"Position","category":"move_human","px":168.7,"py":854.0,"ts_relative":0,"is_bot":false},{"user_id":"a58b4a5f-0add-43fe-b986-1cea83120c5a","event":"Loot","category":"loot","px":168.1,"py":851.7,"ts_relative":0,"is_bot":false},{"user_id":"a58b4a5f-0add-43fe-b986-1cea83120c5a","event":"Position","category":"move_human","px":181.1,"py":836.3,"ts_relative":0,"is_bot":false},{"user_id":"a58b4a5f-0add-43fe-b986-1cea83120c5a","event":"Position","category":"move_human","px":207.2,"py":834.1,"ts_relative":0,"is_bot":false},{"user_id":"a58b4a5f-0add-43fe-b986-1cea83120c5a","event":"BotKill","category":"combat","px":210.0,"py":834.8,"ts_relative":0,"is_bot":false},{"user_id":"a58b4a5f-0add-43fe-b986-1cea83120c5a","event":"Position","category":"move_human","px":215.3,"py":832.7,"ts_relative":0,"is_bot":false},{"user_id":"a58b4a5f-0add-43fe-b986-1cea83120c5a","event":"Loot","category":"loot","px":215.1,"py":832.4,"ts_relative":0,"is_bot":false},{"user_id":"a58b4a5f-0add-43fe-b986-1cea83120c5a","event":"Loot","category":"loot","px":215.1,"py":832.4,"ts_relative":0,"is_bot":false},{"user_id":"a58b4a5f-0add-43fe-b986-1cea83120c5a","event":"Position","category":"move_human","px":220.8,"py":841.9,"ts_relative":0,"is_bot":false},{"user_id":"a58b4a5f-0add-43fe-b986-1cea83120c5a","event":"Position","category":"move_human","px":250.4,"py":825.7,"ts_relative":0,"is_bot":false},{"user_id":"a58b4a5f-0add-43fe-b986-1cea83120c5a","event":"Position","category":"move_human","px":278.7,"py":809.4,"ts_relative":0,"is_bot":false},{"user_id":"a58b4a5f-0add-43fe-b986-1cea83120c5a","event":"Position","category":"move_human","px":300.5,"py":797.3,"ts_relative":0,"is_bot":false},{"user_id":"a58b4a5f-0add-43fe-b986-1cea83120c5a","event":"Loot","category":"loot","px":300.7,"py":798.8,"ts_relative":0,"is_bot":false},{"user_id":"a58b4a5f-0add-43fe-b986-1cea83120c5a","event":"Position","category":"move_human","px":303.9,"py":797.0,"ts_relative":0,"is_bot":false},{"user_id":"a58b4a5f-0add-43fe-b986-1cea83120c5a","event":"Position","category":"move_human","px":320.8,"py":797.0,"ts_relative":0,"is_bot":false},{"user_id":"a58b4a5f-0add-43fe-b986-1cea83120c5a","event":"Position","category":"move_human","px":328.4,"py":804.2,"ts_relative":0,"is_bot":false},{"user_id":"a58b4a5f-0add-43fe-b986-1cea83120c5a","event":"Position","category":"move_human","px":364.3,"py":799.0,"ts_relative":0,"is_bot":false},{"user_id":"a58b4a5f-0add-43fe-b986-1cea83120c5a","event":"Position","category":"move_human","px":395.7,"py":805.9,"ts_relative":0,"is_bot":false},{"user_id":"a58b4a5f-0add-43fe-b986-1cea83120c5a","event":"Loot","category":"loot","px":400.1,"py":823.1,"ts_relative":0,"is_bot":false},{"user_id":"a58b4a5f-0add-43fe-b986-1cea83120c5a","event":"Position","category":"move_human","px":400.5,"py":822.0,"ts_relative":0,"is_bot":false},{"user_id":"a58b4a5f-0add-43fe-b986-1cea83120c5a","event":"Position","category":"move_human","px":413.2,"py":813.5,"ts_relative":0,"is_bot":false},{"user_id":"a58b4a5f-0add-43fe-b986-1cea83120c5a","event":"Loot","category":"loot","px":420.4,"py":800.7,"ts_relative":0,"is_bot":false},{"user_id":"a58b4a5f-0add-43fe-b986-1cea83120c5a","event":"Loot","category":"loot","px":420.3,"py":801.1,"ts_relative":0,"is_bot":false},{"user_id":"a58b4a5f-0add-43fe-b986-1cea83120c5a","event":"Position","category":"move_human","px":420.0,"py":801.3,"ts_relative":0,"is_bot":false},{"user_id":"a58b4a5f-0add-43fe-b986-1cea83120c5a","event":"Position","category":"move_human","px":410.6,"py":801.6,"ts_relative":0,"is_bot":false},{"user_id":"a58b4a5f-0add-43fe-b986-1cea83120c5a","event":"Position","category":"move_human","px":414.4,"py":802.3,"ts_relative":0,"is_bot":false},{"user_id":"a58b4a5f-0add-43fe-b986-1cea83120c5a","event":"Position","category":"move_human","px":420.3,"py":804.1,"ts_relative":0,"is_bot":false},{"user_id":"a58b4a5f-0add-43fe-b986-1cea83120c5a","event":"Position","category":"move_human","px":410.8,"py":810.1,"ts_relative":0,"is_bot":false},{"user_id":"a58b4a5f-0add-43fe-b986-1cea83120c5a","event":"Position","category":"move_human","px":401.2,"py":805.7,"ts_relative":0,"is_bot":false},{"user_id":"a58b4a5f-0add-43fe-b986-1cea83120c5a","event":"Loot","category":"loot","px":401.2,"py":805.7,"ts_relative":0,"is_bot":false},{"user_id":"a58b4a5f-0add-43fe-b986-1cea83120c5a","event":"Position","category":"move_human","px":404.6,"py":802.1,"ts_relative":0,"is_bot":false},{"user_id":"a58b4a5f-0add-43fe-b986-1cea83120c5a","event":"Loot","category":"loot","px":404.6,"py":802.1,"ts_relative":0,"is_bot":false},{"user_id":"a58b4a5f-0add-43fe-b986-1cea83120c5a","event":"Loot","category":"loot","px":406.4,"py":806.0,"ts_relative":0,"is_bot":false},{"user_id":"a58b4a5f-0add-43fe-b986-1cea83120c5a","event":"Position","category":"move_human","px":405.5,"py":806.0,"ts_relative":0,"is_bot":false},{"user_id":"a58b4a5f-0add-43fe-b986-1cea83120c5a","event":"Position","category":"move_human","px":400.7,"py":805.1,"ts_relative":0,"is_bot":false},{"user_id":"a58b4a5f-0add-43fe-b986-1cea83120c5a","event":"Position","category":"move_human","px":403.1,"py":791.9,"ts_relative":0,"is_bot":false},{"user_id":"a58b4a5f-0add-43fe-b986-1cea83120c5a","event":"Position","category":"move_human","px":405.9,"py":804.0,"ts_relative":0,"is_bot":false},{"user_id":"a58b4a5f-0add-43fe-b986-1cea83120c5a","event":"Position","category":"move_human","px":404.8,"py":805.4,"ts_relative":0,"is_bot":false},{"user_id":"a58b4a5f-0add-43fe-b986-1cea83120c5a","event":"Position","category":"move_human","px":403.6,"py":804.0,"ts_relative":0,"is_bot":false},{"user_id":"a58b4a5f-0add-43fe-b986-1cea83120c5a","event":"BotKill","category":"combat","px":412.5,"py":815.7,"ts_relative":0,"is_bot":false},{"user_id":"a58b4a5f-0add-43fe-b986-1cea83120c5a","event":"Position","category":"move_human","px":412.4,"py":815.7,"ts_relative":0,"is_bot":false},{"user_id":"a58b4a5f-0add-43fe-b986-1cea83120c5a","event":"Loot","category":"loot","px":411.7,"py":827.3,"ts_relative":0,"is_bot":false},{"user_id":"a58b4a5f-0add-43fe-b986-1cea83120c5a","event":"Position","category":"move_human","px":411.7,"py":826.4,"ts_relative":0,"is_bot":false},{"user_id":"a58b4a5f-0add-43fe-b986-1cea83120c5a","event":"Loot","category":"loot","px":412.0,"py":827.2,"ts_relative":0,"is_bot":false},{"user_id":"a58b4a5f-0add-43fe-b986-1cea83120c5a","event":"Position","category":"move_human","px":427.5,"py":810.7,"ts_relative":0,"is_bot":false},{"user_id":"a58b4a5f-0add-43fe-b986-1cea83120c5a","event":"Position","category":"move_human","px":448.7,"py":815.1,"ts_relative":0,"is_bot":false},{"user_id":"a58b4a5f-0add-43fe-b986-1cea83120c5a","event":"Position","category":"move_human","px":476.7,"py":825.3,"ts_relative":0,"is_bot":false},{"user_id":"a58b4a5f-0add-43fe-b986-1cea83120c5a","event":"Position","category":"move_human","px":481.0,"py":821.8,"ts_relative":0,"is_bot":false},{"user_id":"a58b4a5f-0add-43fe-b986-1cea83120c5a","event":"BotKill","category":"combat","px":481.5,"py":822.3,"ts_relative":0,"is_bot":false},{"user_id":"a58b4a5f-0add-43fe-b986-1cea83120c5a","event":"Position","category":"move_human","px":477.3,"py":824.8,"ts_relative":0,"is_bot":false},{"user_id":"a58b4a5f-0add-43fe-b986-1cea83120c5a","event":"Position","category":"move_human","px":502.1,"py":833.1,"ts_relative":0,"is_bot":false},{"user_id":"a58b4a5f-0add-43fe-b986-1cea83120c5a","event":"Position","category":"move_human","px":499.2,"py":837.3,"ts_relative":0,"is_bot":false}]}