{"match_id":"9026a0e3-0695-40b5-872c-73a1b4da9c85.nakama-0","map_id":"AmbroseValley","duration_ms":0,"players":[{"user_id":"02bdf800-2916-42ce-9147-0f12dcd1da74","is_bot":false,"events":25}],"events":[{"user_id":"02bdf800-2916-42ce-9147-0f12dcd1da74","event":"Position","category":"move_human","px":722.8,"py":541.9,"ts_relative":0,"is_bot":false},{"user_id":"02bdf800-2916-42ce-9147-0f12dcd1da74","event":"Position","category":"move_human","px":713.4,"py":542.2,"ts_relative":0,"is_bot":false},{"user_id":"02bdf800-2916-42ce-9147-0f12dcd1da74","event":"Position","category":"move_human","px":693.6,"py":545.7,"ts_relative":0,"is_bot":false},{"user_id":"02bdf800-2916-42ce-9147-0f12dcd1da74","event":"Position","category":"move_human","px":675.7,"py":553.5,"ts_relative":0,"is_bot":false},{"user_id":"02bdf800-2916-42ce-9147-0f12dcd1da74","event":"Position","category":"move_human","px":674.2,"py":554.8,"ts_relative":0,"is_bot":false},{"user_id":"02bdf800-2916-42ce-9147-0f12dcd1da74","event":"Position","category":"move_human","px":677.1,"py":560.9,"ts_relative":0,"is_bot":false},{"user_id":"02bdf800-2916-42ce-9147-0f12dcd1da74","event":"Position","category":"move_human","px":685.0,"py":573.7,"ts_relative":0,"is_bot":false},{"user_id":"02bdf800-2916-42ce-9147-0f12dcd1da74","event":"Position","category":"move_human","px":668.3,"py":581.0,"ts_relative":0,"is_bot":false},{"user_id":"02bdf800-2916-42ce-9147-0f12dcd1da74","event":"Position","category":"move_human","px":649.2,"py":577.8,"ts_relative":0,"is_bot":false},{"user_id":"02bdf800-2916-42ce-9147-0f12dcd1da74","event":"Position","category":"move_human","px":645.1,"py":568.7,"ts_relative":0,"is_bot":false},{"user_id":"02bdf800-2916-42ce-9147-0f12dcd1da74","event":"Position","category":"move_human","px":638.2,"py":577.6,"ts_relative":0,"is_bot":false},{"user_id":"02bdf800-2916-42ce-9147-0f12dcd1da74","event":"Loot","category":"loot","px":633.2,"py":578.9,"ts_relative":0,"is_bot":false},{"user_id":"02bdf800-2916-42ce-9147-0f12dcd1da74","event":"Position","category":"move_human","px":633.2,"py":578.9,"ts_relative":0,"is_bot":false},{"user_id":"02bdf800-2916-42ce-9147-0f12dcd1da74","event":"Position","category":"move_human","px":629.6,"py":575.2,"ts_relative":0,"is_bot":false},{"user_id":"02bdf800-2916-42ce-9147-0f12dcd1da74","event":"Position","category":"move_human","px":619.4,"py":586.2,"ts_relative":0,"is_bot":false},{"user_id":"02bdf800-2916-42ce-9147-0f12dcd1da74","event":"Position","category":"move_human","px":613.2,"py":571.8,"ts_relative":0,"is_bot":false},{"user_id":"02bdf800-2916-42ce-9147-0f12dcd1da74","event":"Position","category":"move_human","px":614.5,"py":556.1,"ts_relative":0,"is_bot":false},{"user_id":"02bdf800-2916-42ce-9147-0f12dcd1da74","event":"Position","category":"move_human","px":605.7,"py":541.5,"ts_relative":0,"is_bot":false},{"user_id":"02bdf800-2916-42ce-9147-0f12dcd1da74","event":"Position","category":"move_human","px":595.0,"py":539.4,"ts_relative":0,"is_bot":false},{"user_id":"02bdf800-2916-42ce-9147-0f12dcd1da74","event":"Position","category":"move_human","px":590.5,"py":543.1,"ts_relative":0,"is_bot":false},{"user_id":"02bdf800-2916-42ce-9147-0f12dcd1da74","event":"Position","category":"move_human","px":589.0,"py":552.3,"ts_relative":0,"is_bot":false},{"user_id":"02bdf800-2916-42ce-9147-0f12dcd1da74","event":"Position","category":"move_human","px":575.8,"py":562.9,"ts_relative":0,"is_bot":false},{"user_id":"02bdf800-2916-42ce-9147-0f12dcd1da74","event":"Position","category":"move_human","px":556.1,"py":567.4,"ts_relative":0,"is_bot":false},{"user_id":"02bdf800-2916-42ce-9147-0f12dcd1da74","event":"BotKill","category":"combat","px":555.7,"py":567.4,"ts_relative":0,"is_bot":false},{"user_id":"02bdf800-2916-42ce-9147-0f12dcd1da74","event":"BotKilled","category":"combat","px":555.7,"py":567.4,"ts_relative":0,"is_bot":false}]}