{"match_id":"9b993025-6ebd-490d-9918-9673e3ceca27.nakama-0","map_id":"AmbroseValley","duration_ms":0,"players":[{"user_id":"7604b2ec-89cd-4197-92b7-892d377686bc","is_bot":false,"events":165}],"events":[{"user_id":"7604b2ec-89cd-4197-92b7-892d377686bc","event":"Position","category":"move_human","px":299.7,"py":897.9,"ts_relative":0,"is_bot":false},{"user_id":"7604b2ec-89cd-4197-92b7-892d377686bc","event":"Position","category":"move_human","px":308.4,"py":892.0,"ts_relative":0,"is_bot":false},{"user_id":"7604b2ec-89cd-4197-92b7-892d377686bc","event":"Position","category":"move_human","px":326.6,"py":875.2,"ts_relative":0,"is_bot":false},{"user_id":"7604b2ec-89cd-4197-92b7-892d377686bc","event":"Position","category":"move_human","px":345.6,"py":844.1,"ts_relative":0,"is_bot":false},{"user_id":"7604b2ec-89cd-4197-92b7-892d377686bc","event":"Position","category":"move_human","px":359.6,"py":810.0,"ts_relative":0,"is_bot":false},{"user_id":"7604b2ec-89cd-4197-92b7-892d377686bc","event":"Position","category":"move_human","px":370.2,"py":778.2,"ts_relative":0,"is_bot":false},{"user_id":"7604b2ec-89cd-4197-92b7-892d377686bc","event":"Position","category":"move_human","px":357.6,"py":744.0,"ts_relative":0,"is_bot":false},{"user_id":"7604b2ec-89cd-4197-92b7-892d377686bc","event":"Position","category":"move_human","px":360.2,"py":708.6,"ts_relative":0,"is_bot":false},{"user_id":"7604b2ec-89cd-4197-92b7-892d377686bc","event":"Loot","category":"loot","px":360.3,"py":708.7,"ts_relative":0,"is_bot":false},{"user_id":"7604b2ec-89cd-4197-92b7-892d377686bc","event":"Position","category":"move_human","px":343.1,"py":694.7,"ts_relative":0,"is_bot":false},{"user_id":"7604b2ec-89cd-4197-92b7-892d377686bc","event":"Position","category":"move_human","px":331.0,"py":664.7,"ts_relative":0,"is_bot":false},{"user_id":"7604b2ec-89cd-4197-92b7-892d377686bc","event":"Loot","category":"loot","px":335.6,"py":663.9,"ts_relative":0,"is_bot":false},{"user_id":"7604b2ec-89cd-4197-92b7-892d377686bc","event":"Position","category":"move_human","px":339.2,"py":665.7,"ts_relative":0,"is_bot":false},{"user_id":"7604b2ec-89cd-4197-92b7-892d377686bc","event":"Position","category":"move_human","px":360.8,"py":650.4,"ts_relative":0,"is_bot":false},{"user_id":"7604b2ec-89cd-4197-92b7-892d377686bc","event":"Position","category":"move_human","px":385.8,"py":624.3,"ts_relative":0,"is_bot":false},{"user_id":"7604b2ec-89cd-4197-92b7-892d377686bc","event":"Position","category":"move_human","px":400.6,"py":616.4,"ts_relative":0,"is_bot":false},{"user_id":"7604b2ec-89cd-4197-92b7-892d377686bc","event":"Position","category":"move_human","px":406.5,"py":614.9,"ts_relative":0,"is_bot":false},{"user_id":"7604b2ec-89cd-4197-92b7-892d377686bc","event":"Position","category":"move_human","px":413.2,"py":613.1,"ts_relative":0,"is_bot":false},{"user_id":"7604b2ec-89cd-4197-92b7-892d377686bc","event":"Position","category":"move_human","px":410.9,"py":625.4,"ts_relative":0,"is_bot":false},{"user_id":"7604b2ec-89cd-4197-92b7-892d377686bc","event":"Position","category":"move_human","px":411.6,"py":619.0,"ts_relative":0,"is_bot":false},{"user_id":"7604b2ec-89cd-4197-92b7-892d377686bc","event":"Position","category":"move_human","px":406.5,"py":614.3,"ts_relative":0,"is_bot":false},{"user_id":"7604b2ec-89cd-4197-92b7-892d377686bc","event":"Loot","category":"loot","px":406.9,"py":613.4,"ts_relative":0,"is_bot":false},{"user_id":"7604b2ec-89cd-4197-92b7-892d377686bc","event":"Loot","category":"loot","px":406.9,"py":613.4,"ts_relative":0,"is_bot":false},{"user_id":"7604b2ec-89cd-4197-92b7-892d377686bc","event":"Position","category":"move_human","px":419.1,"py":613.0,"ts_relative":0,"is_bot":false},{"user_id":"7604b2ec-89cd-4197-92b7-892d377686bc","event":"Position","category":"move_human","px":446.4,"py":594.8,"ts_relative":0,"is_bot":false},{"user_id":"7604b2ec-89cd-4197-92b7-892d377686bc","event":"Position","category":"move_human","px":442.1,"py":586.4,"ts_relative":0,"is_bot":false},{"user_id":"7604b2ec-89cd-4197-92b7-892d377686bc","event":"Position","category":"move_human","px":467.2,"py":575.0,"ts_relative":0,"is_bot":false},{"user_id":"7604b2ec-89cd-4197-92b7-892d377686bc","event":"Position","category":"move_human","px":479.6,"py":561.7,"ts_relative":0,"is_bot":false},{"user_id":"7604b2ec-89cd-4197-92b7-892d377686bc","event":"Position","category":"move_human","px":462.2,"py":579.9,"ts_relative":0,"is_bot":false},{"user_id":"7604b2ec-89cd-4197-92b7-892d377686bc","event":"Position","category":"move_human","px":445.3,"py":591.4,"ts_relative":0,"is_bot":false},{"user_id":"7604b2ec-89cd-4197-92b7-892d377686bc","event":"Position","category":"move_human","px":441.7,"py":599.8,"ts_relative":0,"is_bot":false},{"user_id":"7604b2ec-89cd-4197-92b7-892d377686bc","event":"Position","category":"move_human","px":431.9,"py":611.4,"ts_relative":0,"is_bot":false},{"user_id":"7604b2ec-89cd-4197-92b7-892d377686bc","event":"Position","category":"move_human","px":428.1,"py":623.0,"ts_relative":0,"is_bot":false},{"user_id":"7604b2ec-89cd-4197-92b7-892d377686bc","event":"Position","category":"move_human","px":423.7,"py":638.0,"ts_relative":0,"is_bot":false},{"user_id":"7604b2ec-89cd-4197-92b7-892d377686bc","event":"Position","category":"move_human","px":416.4,"py":639.5,"ts_relative":0,"is_bot":false},{"user_id":"7604b2ec-89cd-4197-92b7-892d377686bc","event":"Position","category":"move_human","px":422.6,"py":643.5,"ts_relative":0,"is_bot":false},{"user_id":"7604b2ec-89cd-4197-92b7-892d377686bc","event":"Position","category":"move_human","px":419.5,"py":654.5,"ts_relative":0,"is_bot":false},{"user_id":"7604b2ec-89cd-4197-92b7-892d377686bc","event":"Position","category":"move_human","px":425.6,"py":652.0,"ts_relative":0,"is_bot":false},{"user_id":"7604b2ec-89cd-4197-92b7-892d377686bc","event":"Position","category":"move_human","px":431.3,"py":647.6,"ts_relative":0,"is_bot":false},{"user_id":"7604b2ec-89cd-4197-92b7-892d377686bc","event":"Position","category":"move_human","px":451.6,"py":625.8,"ts_relative":0,"is_bot":false},{"user_id":"7604b2ec-89cd-4197-92b7-892d377686bc","event":"Position","category":"move_human","px":452.5,"py":621.1,"ts_relative":0,"is_bot":false},{"user_id":"7604b2ec-89cd-4197-92b7-892d377686bc","event":"Position","category":"move_human","px":443.9,"py":625.7,"ts_relative":0,"is_bot":false},{"user_id":"7604b2ec-89cd-4197-92b7-892d377686bc","event":"Position","category":"move_human","px":416.3,"py":648.0,"ts_relative":0,"is_bot":false},{"user_id":"7604b2ec-89cd-4197-92b7-892d377686bc","event":"Position","category":"move_human","px":404.3,"py":675.0,"ts_relative":0,"is_bot":false},{"user_id":"7604b2ec-89cd-4197-92b7-892d377686bc","event":"Position","category":"move_human","px":406.0,"py":671.7,"ts_relative":0,"is_bot":false},{"user_id":"7604b2ec-89cd-4197-92b7-892d377686bc","event":"Position","category":"move_human","px":413.2,"py":674.3,"ts_relative":0,"is_bot":false},{"user_id":"7604b2ec-89cd-4197-92b7-892d377686bc","event":"Position","category":"move_human","px":434.4,"py":679.5,"ts_relative":0,"is_bot":false},{"user_id":"7604b2ec-89cd-4197-92b7-892d377686bc","event":"Position","category":"move_human","px":470.2,"py":684.5,"ts_relative":0,"is_bot":false},{"user_id":"7604b2ec-89cd-4197-92b7-892d377686bc","event":"Position","category":"move_human","px":492.2,"py":659.8,"ts_relative":0,"is_bot":false},{"user_id":"7604b2ec-89cd-4197-92b7-892d377686bc","event":"Position","category":"move_human","px":474.9,"py":640.4,"ts_relative":0,"is_bot":false},{"user_id":"7604b2ec-89cd-4197-92b7-892d377686bc","event":"Position","category":"move_human","px":464.8,"py":626.3,"ts_relative":0,"is_bot":false},{"user_id":"7604b2ec-89cd-4197-92b7-892d377686bc","event":"Position","category":"move_human","px":456.1,"py":636.9,"ts_relative":0,"is_bot":false},{"user_id":"7604b2ec-89cd-4197-92b7-892d377686bc","event":"Position","category":"move_human","px":436.6,"py":637.9,"ts_relative":0,"is_bot":false},{"user_id":"7604b2ec-89cd-4197-92b7-892d377686bc","event":"Position","category":"move_human","px":433.9,"py":642.1,"ts_relative":0,"is_bot":false},{"user_id":"7604b2ec-89cd-4197-92b7-892d377686bc","event":"Position","category":"move_human","px":433.1,"py":649.4,"ts_relative":0,"is_bot":false},{"user_id":"7604b2ec-89cd-4197-92b7-892d377686bc","event":"Position","category":"move_human","px":428.0,"py":654.8,"ts_relative":0,"is_bot":false},{"user_id":"7604b2ec-89cd-4197-92b7-892d377686bc","event":"Position","category":"move_human","px":422.0,"py":660.0,"ts_relative":0,"is_bot":false},{"user_id":"7604b2ec-89cd-4197-92b7-892d377686bc","event":"Position","category":"move_human","px":419.7,"py":656.2,"ts_relative":0,"is_bot":false},{"user_id":"7604b2ec-89cd-4197-92b7-892d377686bc","event":"Position","category":"move_human","px":416.7,"py":678.0,"ts_relative":0,"is_bot":false},{"user_id":"7604b2ec-89cd-4197-92b7-892d377686bc","event":"Position","category":"move_human","px":403.5,"py":706.5,"ts_relative":0,"is_bot":false},{"user_id":"7604b2ec-89cd-4197-92b7-892d377686bc","event":"Position","category":"move_human","px":404.6,"py":705.1,"ts_relative":0,"is_bot":false},{"user_id":"7604b2ec-89cd-4197-92b7-892d377686bc","event":"Position","category":"move_human","px":401.3,"py":690.7,"ts_relative":0,"is_bot":false},{"user_id":"7604b2ec-89cd-4197-92b7-892d377686bc","event":"Position","category":"move_human","px":402.5,"py":670.9,"ts_relative":0,"is_bot":false},{"user_id":"7604b2ec-89cd-4197-92b7-892d377686bc","event":"Position","category":"move_human","px":404.5,"py":658.9,"ts_relative":0,"is_bot":false},{"user_id":"7604b2ec-89cd-4197-92b7-892d377686bc","event":"Position","category":"move_human","px":417.4,"py":646.4,"ts_relative":0,"is_bot":false},{"user_id":"7604b2ec-89cd-4197-92b7-892d377686bc","event":"Position","category":"move_human","px":423.3,"py":635.2,"ts_relative":0,"is_bot":false},{"user_id":"7604b2ec-89cd-4197-92b7-892d377686bc","event":"Position","category":"move_human","px":416.5,"py":661.5,"ts_relative":0,"is_bot":false},{"user_id":"7604b2ec-89cd-4197-92b7-892d377686bc","event":"Position","category":"move_human","px":401.3,"py":693.4,"ts_relative":0,"is_bot":false},{"user_id":"7604b2ec-89cd-4197-92b7-892d377686bc","event":"Position","category":"move_human","px":390.6,"py":707.7,"ts_relative":0,"is_bot":false},{"user_id":"7604b2ec-89cd-4197-92b7-892d377686bc","event":"Position","category":"move_human","px":383.8,"py":707.3,"ts_relative":0,"is_bot":false},{"user_id":"7604b2ec-89cd-4197-92b7-892d377686bc","event":"Position","category":"move_human","px":372.7,"py":716.0,"ts_relative":0,"is_bot":false},{"user_id":"7604b2ec-89cd-4197-92b7-892d377686bc","event":"Position","category":"move_human","px":354.9,"py":712.4,"ts_relative":0,"is_bot":false},{"user_id":"7604b2ec-89cd-4197-92b7-892d377686bc","event":"Loot","category":"loot","px":354.9,"py":712.4,"ts_relative":0,"is_bot":false},{"user_id":"7604b2ec-89cd-4197-92b7-892d377686bc","event":"Loot","category":"loot","px":354.9,"py":712.4,"ts_relative":0,"is_bot":false},{"user_id":"7604b2ec-89cd-4197-92b7-892d377686bc","event":"Position","category":"move_human","px":345.4,"py":697.6,"ts_relative":0,"is_bot":false},{"user_id":"7604b2ec-89cd-4197-92b7-892d377686bc","event":"Position","category":"move_human","px":340.1,"py":666.3,"ts_relative":0,"is_bot":false},{"user_id":"7604b2ec-89cd-4197-92b7-892d377686bc","event":"Position","category":"move_human","px":364.1,"py":641.1,"ts_relative":0,"is_bot":false},{"user_id":"7604b2ec-89cd-4197-92b7-892d377686bc","event":"Position","category":"move_human","px":378.0,"py":615.5,"ts_relative":0,"is_bot":false},{"user_id":"7604b2ec-89cd-4197-92b7-892d377686bc","event":"Position","category":"move_human","px":382.6,"py":609.6,"ts_relative":0,"is_bot":false},{"user_id":"7604b2ec-89cd-4197-92b7-892d377686bc","event":"Position","category":"move_human","px":387.1,"py":606.9,"ts_relative":0,"is_bot":false},{"user_id":"7604b2ec-89cd-4197-92b7-892d377686bc","event":"Position","category":"move_human","px":388.9,"py":604.4,"ts_relative":0,"is_bot":false},{"user_id":"7604b2ec-89cd-4197-92b7-892d377686bc","event":"Position","category":"move_human","px":394.0,"py":596.8,"ts_relative":0,"is_bot":false},{"user_id":"7604b2ec-89cd-4197-92b7-892d377686bc","event":"Position","category":"move_human","px":405.0,"py":587.9,"ts_relative":0,"is_bot":false},{"user_id":"7604b2ec-89cd-4197-92b7-892d377686bc","event":"Loot","category":"loot","px":412.1,"py":588.4,"ts_relative":0,"is_bot":false},{"user_id":"7604b2ec-89cd-4197-92b7-892d377686bc","event":"Position","category":"move_human","px":412.7,"py":586.7,"ts_relative":0,"is_bot":false},{"user_id":"7604b2ec-89cd-4197-92b7-892d377686bc","event":"Loot","category":"loot","px":427.6,"py":594.0,"ts_relative":0,"is_bot":false},{"user_id":"7604b2ec-89cd-4197-92b7-892d377686bc","event":"Loot","category":"loot","px":427.6,"py":594.0,"ts_relative":0,"is_bot":false},{"user_id":"7604b2ec-89cd-4197-92b7-892d377686bc","event":"Loot","category":"loot","px":427.6,"py":594.0,"ts_relative":0,"is_bot":false},{"user_id":"7604b2ec-89cd-4197-92b7-892d377686bc","event":"Position","category":"move_human","px":427.8,"py":594.2,"ts_relative":0,"is_bot":false},{"user_id":"7604b2ec-89cd-4197-92b7-892d377686bc","event":"Loot","category":"loot","px":434.2,"py":599.8,"ts_relative":0,"is_bot":false},{"user_id":"7604b2ec-89cd-4197-92b7-892d377686bc","event":"Position","category":"move_human","px":440.2,"py":597.4,"ts_relative":0,"is_bot":false},{"user_id":"7604b2ec-89cd-4197-92b7-892d377686bc","event":"Loot","category":"loot","px":440.4,"py":597.5,"ts_relative":0,"is_bot":false},{"user_id":"7604b2ec-89cd-4197-92b7-892d377686bc","event":"Loot","category":"loot","px":440.4,"py":597.5,"ts_relative":0,"is_bot":false},{"user_id":"7604b2ec-89cd-4197-92b7-892d377686bc","event":"Position","category":"move_human","px":435.2,"py":595.6,"ts_relative":0,"is_bot":false},{"user_id":"7604b2ec-89cd-4197-92b7-892d377686bc","event":"Position","category":"move_human","px":419.7,"py":578.0,"ts_relative":0,"is_bot":false},{"user_id":"7604b2ec-89cd-4197-92b7-892d377686bc","event":"Position","category":"move_human","px":420.2,"py":550.4,"ts_relative":0,"is_bot":false},{"user_id":"7604b2ec-89cd-4197-92b7-892d377686bc","event":"Position","category":"move_human","px":426.3,"py":525.9,"ts_relative":0,"is_bot":false},{"user_id":"7604b2ec-89cd-4197-92b7-892d377686bc","event":"Position","category":"move_human","px":423.3,"py":513.5,"ts_relative":0,"is_bot":false},{"user_id":"7604b2ec-89cd-4197-92b7-892d377686bc","event":"Loot","category":"loot","px":423.2,"py":495.9,"ts_relative":0,"is_bot":false},{"user_id":"7604b2ec-89cd-4197-92b7-892d377686bc","event":"Loot","category":"loot","px":423.2,"py":495.9,"ts_relative":0,"is_bot":false},{"user_id":"7604b2ec-89cd-4197-92b7-892d377686bc","event":"Position","category":"move_human","px":423.3,"py":496.3,"ts_relative":0,"is_bot":false},{"user_id":"7604b2ec-89cd-4197-92b7-892d377686bc","event":"Loot","category":"loot","px":423.4,"py":487.3,"ts_relative":0,"is_bot":false},{"user_id":"7604b2ec-89cd-4197-92b7-892d377686bc","event":"Loot","category":"loot","px":423.4,"py":487.3,"ts_relative":0,"is_bot":false},{"user_id":"7604b2ec-89cd-4197-92b7-892d377686bc","event":"Loot","category":"loot","px":423.4,"py":487.3,"ts_relative":0,"is_bot":false},{"user_id":"7604b2ec-89cd-4197-92b7-892d377686bc","event":"Loot","category":"loot","px":423.4,"py":487.3,"ts_relative":0,"is_bot":false},{"user_id":"7604b2ec-89cd-4197-92b7-892d377686bc","event":"Position","category":"move_human","px":422.2,"py":482.5,"ts_relative":0,"is_bot":false},{"user_id":"7604b2ec-89cd-4197-92b7-892d377686bc","event":"Position","category":"move_human","px":423.1,"py":475.8,"ts_relative":0,"is_bot":false},{"user_id":"7604b2ec-89cd-4197-92b7-892d377686bc","event":"BotKill","category":"combat","px":425.8,"py":482.2,"ts_relative":0,"is_bot":false},{"user_id":"7604b2ec-89cd-4197-92b7-892d377686bc","event":"Position","category":"move_human","px":426.9,"py":486.3,"ts_relative":0,"is_bot":false},{"user_id":"7604b2ec-89cd-4197-92b7-892d377686bc","event":"Loot","category":"loot","px":427.0,"py":485.6,"ts_relative":0,"is_bot":false},{"user_id":"7604b2ec-89cd-4197-92b7-892d377686bc","event":"Position","category":"move_human","px":432.0,"py":459.8,"ts_relative":0,"is_bot":false},{"user_id":"7604b2ec-89cd-4197-92b7-892d377686bc","event":"Position","category":"move_human","px":453.9,"py":436.7,"ts_relative":0,"is_bot":false},{"user_id":"7604b2ec-89cd-4197-92b7-892d377686bc","event":"Position","category":"move_human","px":482.3,"py":421.0,"ts_relative":0,"is_bot":false},{"user_id":"7604b2ec-89cd-4197-92b7-892d377686bc","event":"Position","category":"move_human","px":511.9,"py":398.8,"ts_relative":0,"is_bot":false},{"user_id":"7604b2ec-89cd-4197-92b7-892d377686bc","event":"Loot","category":"loot","px":525.0,"py":393.7,"ts_relative":0,"is_bot":false},{"user_id":"7604b2ec-89cd-4197-92b7-892d377686bc","event":"Loot","category":"loot","px":525.0,"py":393.7,"ts_relative":0,"is_bot":false},{"user_id":"7604b2ec-89cd-4197-92b7-892d377686bc","event":"Position","category":"move_human","px":528.5,"py":382.2,"ts_relative":0,"is_bot":false},{"user_id":"7604b2ec-89cd-4197-92b7-892d377686bc","event":"Loot","category":"loot","px":533.0,"py":367.2,"ts_relative":0,"is_bot":false},{"user_id":"7604b2ec-89cd-4197-92b7-892d377686bc","event":"Position","category":"move_human","px":533.0,"py":367.2,"ts_relative":0,"is_bot":false},{"user_id":"7604b2ec-89cd-4197-92b7-892d377686bc","event":"Loot","category":"loot","px":533.0,"py":367.2,"ts_relative":0,"is_bot":false},{"user_id":"7604b2ec-89cd-4197-92b7-892d377686bc","event":"Position","category":"move_human","px":537.2,"py":364.4,"ts_relative":0,"is_bot":false},{"user_id":"7604b2ec-89cd-4197-92b7-892d377686bc","event":"Position","category":"move_human","px":513.1,"py":338.5,"ts_relative":0,"is_bot":false},{"user_id":"7604b2ec-89cd-4197-92b7-892d377686bc","event":"Position","category":"move_human","px":477.2,"py":339.2,"ts_relative":0,"is_bot":false},{"user_id":"7604b2ec-89cd-4197-92b7-892d377686bc","event":"Position","category":"move_human","px":449.7,"py":363.7,"ts_relative":0,"is_bot":false},{"user_id":"7604b2ec-89cd-4197-92b7-892d377686bc","event":"Position","category":"move_human","px":427.9,"py":383.5,"ts_relative":0,"is_bot":false},{"user_id":"7604b2ec-89cd-4197-92b7-892d377686bc","event":"Position","category":"move_human","px":420.4,"py":384.5,"ts_relative":0,"is_bot":false},{"user_id":"7604b2ec-89cd-4197-92b7-892d377686bc","event":"Position","category":"move_human","px":422.7,"py":384.9,"ts_relative":0,"is_bot":false},{"user_id":"7604b2ec-89cd-4197-92b7-892d377686bc","event":"Position","category":"move_human","px":429.2,"py":381.5,"ts_relative":0,"is_bot":false},{"user_id":"7604b2ec-89cd-4197-92b7-892d377686bc","event":"Position","category":"move_human","px":432.9,"py":378.4,"ts_relative":0,"is_bot":false},{"user_id":"7604b2ec-89cd-4197-92b7-892d377686bc","event":"Position","category":"move_human","px":432.2,"py":379.1,"ts_relative":0,"is_bot":false},{"user_id":"7604b2ec-89cd-4197-92b7-892d377686bc","event":"Position","category":"move_human","px":427.4,"py":383.8,"ts_relative":0,"is_bot":false},{"user_id":"7604b2ec-89cd-4197-92b7-892d377686bc","event":"Position","category":"move_human","px":416.3,"py":385.2,"ts_relative":0,"is_bot":false},{"user_id":"7604b2ec-89cd-4197-92b7-892d377686bc","event":"Position","category":"move_human","px":394.7,"py":397.6,"ts_relative":0,"is_bot":false},{"user_id":"7604b2ec-89cd-4197-92b7-892d377686bc","event":"Loot","category":"loot","px":395.2,"py":397.8,"ts_relative":0,"is_bot":false},{"user_id":"7604b2ec-89cd-4197-92b7-892d377686bc","event":"Loot","category":"loot","px":395.2,"py":397.8,"ts_relative":0,"is_bot":false},{"user_id":"7604b2ec-89cd-4197-92b7-892d377686bc","event":"Position","category":"move_human","px":390.2,"py":375.9,"ts_relative":0,"is_bot":false},{"user_id":"7604b2ec-89cd-4197-92b7-892d377686bc","event":"Position","category":"move_human","px":384.5,"py":348.1,"ts_relative":0,"is_bot":false},{"user_id":"7604b2ec-89cd-4197-92b7-892d377686bc","event":"Position","category":"move_human","px":382.0,"py":315.0,"ts_relative":0,"is_bot":false},{"user_id":"7604b2ec-89cd-4197-92b7-892d377686bc","event":"Position","category":"move_human","px":373.1,"py":283.1,"ts_relative":0,"is_bot":false},{"user_id":"7604b2ec-89cd-4197-92b7-892d377686bc","event":"Position","category":"move_human","px":358.6,"py":267.8,"ts_relative":0,"is_bot":false},{"user_id":"7604b2ec-89cd-4197-92b7-892d377686bc","event":"Position","category":"move_human","px":342.0,"py":259.1,"ts_relative":0,"is_bot":false},{"user_id":"7604b2ec-89cd-4197-92b7-892d377686bc","event":"Position","category":"move_human","px":316.8,"py":242.7,"ts_relative":0,"is_bot":false},{"user_id":"7604b2ec-89cd-4197-92b7-892d377686bc","event":"Position","category":"move_human","px":323.8,"py":240.3,"ts_relative":0,"is_bot":false},{"user_id":"7604b2ec-89cd-4197-92b7-892d377686bc","event":"Position","category":"move_human","px":349.5,"py":250.2,"ts_relative":0,"is_bot":false},{"user_id":"7604b2ec-89cd-4197-92b7-892d377686bc","event":"Position","category":"move_human","px":382.5,"py":252.6,"ts_relative":0,"is_bot":false},{"user_id":"7604b2ec-89cd-4197-92b7-892d377686bc","event":"Position","category":"move_human","px":412.0,"py":266.8,"ts_relative":0,"is_bot":false},{"user_id":"7604b2ec-89cd-4197-92b7-892d377686bc","event":"Position","category":"move_human","px":439.0,"py":282.7,"ts_relative":0,"is_bot":false},{"user_id":"7604b2ec-89cd-4197-92b7-892d377686bc","event":"Position","category":"move_human","px":459.0,"py":296.4,"ts_relative":0,"is_bot":false},{"user_id":"7604b2ec-89cd-4197-92b7-892d377686bc","event":"Position","category":"move_human","px":484.0,"py":318.2,"ts_relative":0,"is_bot":false},{"user_id":"7604b2ec-89cd-4197-92b7-892d377686bc","event":"Position","category":"move_human","px":500.6,"py":330.5,"ts_relative":0,"is_bot":false},{"user_id":"7604b2ec-89cd-4197-92b7-892d377686bc","event":"Position","category":"move_human","px":525.0,"py":342.4,"ts_relative":0,"is_bot":false},{"user_id":"7604b2ec-89cd-4197-92b7-892d377686bc","event":"Position","category":"move_human","px":555.8,"py":334.0,"ts_relative":0,"is_bot":false},{"user_id":"7604b2ec-89cd-4197-92b7-892d377686bc","event":"Position","category":"move_human","px":581.3,"py":336.7,"ts_relative":0,"is_bot":false},{"user_id":"7604b2ec-89cd-4197-92b7-892d377686bc","event":"Position","category":"move_human","px":606.5,"py":345.9,"ts_relative":0,"is_bot":false},{"user_id":"7604b2ec-89cd-4197-92b7-892d377686bc","event":"Position","category":"move_human","px":616.9,"py":371.6,"ts_relative":0,"is_bot":false},{"user_id":"7604b2ec-89cd-4197-92b7-892d377686bc","event":"Position","category":"move_human","px":640.6,"py":378.7,"ts_relative":0,"is_bot":false},{"user_id":"7604b2ec-89cd-4197-92b7-892d377686bc","event":"Position","category":"move_human","px":649.3,"py":408.1,"ts_relative":0,"is_bot":false},{"user_id":"7604b2ec-89cd-4197-92b7-892d377686bc","event":"Position","category":"move_human","px":648.6,"py":430.3,"ts_relative":0,"is_bot":false},{"user_id":"7604b2ec-89cd-4197-92b7-892d377686bc","event":"Position","category":"move_human","px":640.2,"py":461.2,"ts_relative":0,"is_bot":false},{"user_id":"7604b2ec-89cd-4197-92b7-892d377686bc","event":"Position","category":"move_human","px":641.5,"py":482.8,"ts_relative":0,"is_bot":false},{"user_id":"7604b2ec-89cd-4197-92b7-892d377686bc","event":"Position","category":"move_human","px":634.7,"py":512.5,"ts_relative":0,"is_bot":false},{"user_id":"7604b2ec-89cd-4197-92b7-892d377686bc","event":"Position","category":"move_human","px":626.5,"py":535.4,"ts_relative":0,"is_bot":false},{"user_id":"7604b2ec-89cd-4197-92b7-892d377686bc","event":"Position","category":"move_human","px":632.0,"py":551.6,"ts_relative":0,"is_bot":false},{"user_id":"7604b2ec-89cd-4197-92b7-892d377686bc","event":"Position","category":"move_human","px":644.0,"py":564.3,"ts_relative":0,"is_bot":false},{"user_id":"7604b2ec-89cd-4197-92b7-892d377686bc","event":"Position","category":"move_human","px":645.6,"py":567.0,"ts_relative":0,"is_bot":false}]}