{"match_id":"ae12ac8c-0b2e-4abb-8545-67bb3bee3d18.nakama-0","map_id":"GrandRift","duration_ms":0,"players":[{"user_id":"94d042cb-a0f2-45f3-bdca-42fab73cfef5","is_bot":false,"events":142}],"events":[{"user_id":"94d042cb-a0f2-45f3-bdca-42fab73cfef5","event":"Position","category":"move_human","px":117.7,"py":437.6,"ts_relative":0,"is_bot":false},{"user_id":"94d042cb-a0f2-45f3-bdca-42fab73cfef5","event":"Position","category":"move_human","px":147.3,"py":446.0,"ts_relative":0,"is_bot":false},{"user_id":"94d042cb-a0f2-45f3-bdca-42fab73cfef5","event":"Position","category":"move_human","px":198.7,"py":455.8,"ts_relative":0,"is_bot":false},{"user_id":"94d042cb-a0f2-45f3-bdca-42fab73cfef5","event":"Position","category":"move_human","px":214.4,"py":461.9,"ts_relative":0,"is_bot":false},{"user_id":"94d042cb-a0f2-45f3-bdca-42fab73cfef5","event":"Position","category":"move_human","px":230.5,"py":474.6,"ts_relative":0,"is_bot":false},{"user_id":"94d042cb-a0f2-45f3-bdca-42fab73cfef5","event":"Loot","category":"loot","px":226.3,"py":495.6,"ts_relative":0,"is_bot":false},{"user_id":"94d042cb-a0f2-45f3-bdca-42fab73cfef5","event":"Position","category":"move_human","px":228.1,"py":500.8,"ts_relative":0,"is_bot":false},{"user_id":"94d042cb-a0f2-45f3-bdca-42fab73cfef5","event":"Position","category":"move_human","px":237.7,"py":523.0,"ts_relative":0,"is_bot":false},{"user_id":"94d042cb-a0f2-45f3-bdca-42fab73cfef5","event":"Loot","category":"loot","px":240.8,"py":527.4,"ts_relative":0,"is_bot":false},{"user_id":"94d042cb-a0f2-45f3-bdca-42fab73cfef5","event":"Position","category":"move_human","px":229.6,"py":529.9,"ts_relative":0,"is_bot":false},{"user_id":"94d042cb-a0f2-45f3-bdca-42fab73cfef5","event":"Position","category":"move_human","px":256.9,"py":551.8,"ts_relative":0,"is_bot":false},{"user_id":"94d042cb-a0f2-45f3-bdca-42fab73cfef5","event":"Position","category":"move_human","px":302.9,"py":546.3,"ts_relative":0,"is_bot":false},{"user_id":"94d042cb-a0f2-45f3-bdca-42fab73cfef5","event":"Position","category":"move_human","px":317.5,"py":531.2,"ts_relative":0,"is_bot":false},{"user_id":"94d042cb-a0f2-45f3-bdca-42fab73cfef5","event":"Position","category":"move_human","px":315.1,"py":525.9,"ts_relative":0,"is_bot":false},{"user_id":"94d042cb-a0f2-45f3-bdca-42fab73cfef5","event":"Position","category":"move_human","px":317.5,"py":517.8,"ts_relative":0,"is_bot":false},{"user_id":"94d042cb-a0f2-45f3-bdca-42fab73cfef5","event":"BotKill","category":"combat","px":322.1,"py":511.9,"ts_relative":0,"is_bot":false},{"user_id":"94d042cb-a0f2-45f3-bdca-42fab73cfef5","event":"Position","category":"move_human","px":328.9,"py":510.3,"ts_relative":0,"is_bot":false},{"user_id":"94d042cb-a0f2-45f3-bdca-42fab73cfef5","event":"Position","category":"move_human","px":337.6,"py":504.3,"ts_relative":0,"is_bot":false},{"user_id":"94d042cb-a0f2-45f3-bdca-42fab73cfef5","event":"Position","category":"move_human","px":338.5,"py":503.8,"ts_relative":0,"is_bot":false},{"user_id":"94d042cb-a0f2-45f3-bdca-42fab73cfef5","event":"BotKill","category":"combat","px":338.5,"py":503.8,"ts_relative":0,"is_bot":false},{"user_id":"94d042cb-a0f2-45f3-bdca-42fab73cfef5","event":"Position","category":"move_human","px":339.9,"py":505.8,"ts_relative":0,"is_bot":false},{"user_id":"94d042cb-a0f2-45f3-bdca-42fab73cfef5","event":"Position","category":"move_human","px":353.0,"py":505.4,"ts_relative":0,"is_bot":false},{"user_id":"94d042cb-a0f2-45f3-bdca-42fab73cfef5","event":"Position","category":"move_human","px":352.0,"py":504.4,"ts_relative":0,"is_bot":false},{"user_id":"94d042cb-a0f2-45f3-bdca-42fab73cfef5","event":"Loot","category":"loot","px":369.1,"py":494.2,"ts_relative":0,"is_bot":false},{"user_id":"94d042cb-a0f2-45f3-bdca-42fab73cfef5","event":"Position","category":"move_human","px":377.7,"py":486.6,"ts_relative":0,"is_bot":false},{"user_id":"94d042cb-a0f2-45f3-bdca-42fab73cfef5","event":"Loot","category":"loot","px":385.0,"py":482.9,"ts_relative":0,"is_bot":false},{"user_id":"94d042cb-a0f2-45f3-bdca-42fab73cfef5","event":"Position","category":"move_human","px":384.1,"py":483.2,"ts_relative":0,"is_bot":false},{"user_id":"94d042cb-a0f2-45f3-bdca-42fab73cfef5","event":"Position","category":"move_human","px":377.7,"py":483.4,"ts_relative":0,"is_bot":false},{"user_id":"94d042cb-a0f2-45f3-bdca-42fab73cfef5","event":"Position","category":"move_human","px":364.7,"py":490.1,"ts_relative":0,"is_bot":false},{"user_id":"94d042cb-a0f2-45f3-bdca-42fab73cfef5","event":"Position","category":"move_human","px":374.2,"py":493.4,"ts_relative":0,"is_bot":false},{"user_id":"94d042cb-a0f2-45f3-bdca-42fab73cfef5","event":"Position","category":"move_human","px":408.1,"py":504.5,"ts_relative":0,"is_bot":false},{"user_id":"94d042cb-a0f2-45f3-bdca-42fab73cfef5","event":"Position","category":"move_human","px":455.5,"py":521.6,"ts_relative":0,"is_bot":false},{"user_id":"94d042cb-a0f2-45f3-bdca-42fab73cfef5","event":"Position","category":"move_human","px":465.6,"py":520.8,"ts_relative":0,"is_bot":false},{"user_id":"94d042cb-a0f2-45f3-bdca-42fab73cfef5","event":"Loot","category":"loot","px":465.6,"py":520.8,"ts_relative":0,"is_bot":false},{"user_id":"94d042cb-a0f2-45f3-bdca-42fab73cfef5","event":"Loot","category":"loot","px":465.6,"py":520.8,"ts_relative":0,"is_bot":false},{"user_id":"94d042cb-a0f2-45f3-bdca-42fab73cfef5","event":"Position","category":"move_human","px":456.3,"py":515.6,"ts_relative":0,"is_bot":false},{"user_id":"94d042cb-a0f2-45f3-bdca-42fab73cfef5","event":"Position","category":"move_human","px":459.0,"py":541.8,"ts_relative":0,"is_bot":false},{"user_id":"94d042cb-a0f2-45f3-bdca-42fab73cfef5","event":"Position","category":"move_human","px":463.8,"py":535.4,"ts_relative":0,"is_bot":false},{"user_id":"94d042cb-a0f2-45f3-bdca-42fab73cfef5","event":"Position","category":"move_human","px":457.1,"py":531.2,"ts_relative":0,"is_bot":false},{"user_id":"94d042cb-a0f2-45f3-bdca-42fab73cfef5","event":"Position","category":"move_human","px":446.6,"py":513.9,"ts_relative":0,"is_bot":false},{"user_id":"94d042cb-a0f2-45f3-bdca-42fab73cfef5","event":"BotKill","category":"combat","px":455.7,"py":503.5,"ts_relative":0,"is_bot":false},{"user_id":"94d042cb-a0f2-45f3-bdca-42fab73cfef5","event":"Position","category":"move_human","px":459.4,"py":493.1,"ts_relative":0,"is_bot":false},{"user_id":"94d042cb-a0f2-45f3-bdca-42fab73cfef5","event":"Loot","category":"loot","px":459.6,"py":490.9,"ts_relative":0,"is_bot":false},{"user_id":"94d042cb-a0f2-45f3-bdca-42fab73cfef5","event":"Position","category":"move_human","px":470.9,"py":485.5,"ts_relative":0,"is_bot":false},{"user_id":"94d042cb-a0f2-45f3-bdca-42fab73cfef5","event":"Position","category":"move_human","px":464.8,"py":479.8,"ts_relative":0,"is_bot":false},{"user_id":"94d042cb-a0f2-45f3-bdca-42fab73cfef5","event":"BotKill","category":"combat","px":476.7,"py":487.6,"ts_relative":0,"is_bot":false},{"user_id":"94d042cb-a0f2-45f3-bdca-42fab73cfef5","event":"Position","category":"move_human","px":476.7,"py":487.6,"ts_relative":0,"is_bot":false},{"user_id":"94d042cb-a0f2-45f3-bdca-42fab73cfef5","event":"Position","category":"move_human","px":479.4,"py":480.1,"ts_relative":0,"is_bot":false},{"user_id":"94d042cb-a0f2-45f3-bdca-42fab73cfef5","event":"Position","category":"move_human","px":499.0,"py":459.7,"ts_relative":0,"is_bot":false},{"user_id":"94d042cb-a0f2-45f3-bdca-42fab73cfef5","event":"Loot","category":"loot","px":509.2,"py":445.5,"ts_relative":0,"is_bot":false},{"user_id":"94d042cb-a0f2-45f3-bdca-42fab73cfef5","event":"Loot","category":"loot","px":510.5,"py":446.0,"ts_relative":0,"is_bot":false},{"user_id":"94d042cb-a0f2-45f3-bdca-42fab73cfef5","event":"Position","category":"move_human","px":508.3,"py":454.2,"ts_relative":0,"is_bot":false},{"user_id":"94d042cb-a0f2-45f3-bdca-42fab73cfef5","event":"Position","category":"move_human","px":523.0,"py":447.9,"ts_relative":0,"is_bot":false},{"user_id":"94d042cb-a0f2-45f3-bdca-42fab73cfef5","event":"Position","category":"move_human","px":532.3,"py":490.5,"ts_relative":0,"is_bot":false},{"user_id":"94d042cb-a0f2-45f3-bdca-42fab73cfef5","event":"Position","category":"move_human","px":531.5,"py":507.8,"ts_relative":0,"is_bot":false},{"user_id":"94d042cb-a0f2-45f3-bdca-42fab73cfef5","event":"Position","category":"move_human","px":532.8,"py":515.0,"ts_relative":0,"is_bot":false},{"user_id":"94d042cb-a0f2-45f3-bdca-42fab73cfef5","event":"Loot","category":"loot","px":529.6,"py":528.0,"ts_relative":0,"is_bot":false},{"user_id":"94d042cb-a0f2-45f3-bdca-42fab73cfef5","event":"Position","category":"move_human","px":529.6,"py":528.0,"ts_relative":0,"is_bot":false},{"user_id":"94d042cb-a0f2-45f3-bdca-42fab73cfef5","event":"Position","category":"move_human","px":522.4,"py":550.3,"ts_relative":0,"is_bot":false},{"user_id":"94d042cb-a0f2-45f3-bdca-42fab73cfef5","event":"Loot","category":"loot","px":522.4,"py":550.3,"ts_relative":0,"is_bot":false},{"user_id":"94d042cb-a0f2-45f3-bdca-42fab73cfef5","event":"Position","category":"move_human","px":535.8,"py":565.9,"ts_relative":0,"is_bot":false},{"user_id":"94d042cb-a0f2-45f3-bdca-42fab73cfef5","event":"Position","category":"move_human","px":518.1,"py":551.9,"ts_relative":0,"is_bot":false},{"user_id":"94d042cb-a0f2-45f3-bdca-42fab73cfef5","event":"Position","category":"move_human","px":492.0,"py":538.5,"ts_relative":0,"is_bot":false},{"user_id":"94d042cb-a0f2-45f3-bdca-42fab73cfef5","event":"Position","category":"move_human","px":472.2,"py":570.4,"ts_relative":0,"is_bot":false},{"user_id":"94d042cb-a0f2-45f3-bdca-42fab73cfef5","event":"Position","category":"move_human","px":480.7,"py":571.6,"ts_relative":0,"is_bot":false},{"user_id":"94d042cb-a0f2-45f3-bdca-42fab73cfef5","event":"BotKill","category":"combat","px":478.0,"py":567.7,"ts_relative":0,"is_bot":false},{"user_id":"94d042cb-a0f2-45f3-bdca-42fab73cfef5","event":"Position","category":"move_human","px":473.3,"py":568.2,"ts_relative":0,"is_bot":false},{"user_id":"94d042cb-a0f2-45f3-bdca-42fab73cfef5","event":"Position","category":"move_human","px":455.6,"py":580.6,"ts_relative":0,"is_bot":false},{"user_id":"94d042cb-a0f2-45f3-bdca-42fab73cfef5","event":"Position","category":"move_human","px":403.9,"py":586.3,"ts_relative":0,"is_bot":false},{"user_id":"94d042cb-a0f2-45f3-bdca-42fab73cfef5","event":"Position","category":"move_human","px":356.9,"py":592.2,"ts_relative":0,"is_bot":false},{"user_id":"94d042cb-a0f2-45f3-bdca-42fab73cfef5","event":"Position","category":"move_human","px":332.4,"py":580.6,"ts_relative":0,"is_bot":false},{"user_id":"94d042cb-a0f2-45f3-bdca-42fab73cfef5","event":"Position","category":"move_human","px":315.1,"py":552.5,"ts_relative":0,"is_bot":false},{"user_id":"94d042cb-a0f2-45f3-bdca-42fab73cfef5","event":"Position","category":"move_human","px":282.7,"py":509.7,"ts_relative":0,"is_bot":false},{"user_id":"94d042cb-a0f2-45f3-bdca-42fab73cfef5","event":"Position","category":"move_human","px":277.0,"py":452.7,"ts_relative":0,"is_bot":false},{"user_id":"94d042cb-a0f2-45f3-bdca-42fab73cfef5","event":"Position","category":"move_human","px":260.4,"py":413.2,"ts_relative":0,"is_bot":false},{"user_id":"94d042cb-a0f2-45f3-bdca-42fab73cfef5","event":"Loot","category":"loot","px":259.6,"py":402.5,"ts_relative":0,"is_bot":false},{"user_id":"94d042cb-a0f2-45f3-bdca-42fab73cfef5","event":"Position","category":"move_human","px":263.9,"py":404.2,"ts_relative":0,"is_bot":false},{"user_id":"94d042cb-a0f2-45f3-bdca-42fab73cfef5","event":"Loot","category":"loot","px":277.0,"py":391.0,"ts_relative":0,"is_bot":false},{"user_id":"94d042cb-a0f2-45f3-bdca-42fab73cfef5","event":"Position","category":"move_human","px":277.6,"py":399.9,"ts_relative":0,"is_bot":false},{"user_id":"94d042cb-a0f2-45f3-bdca-42fab73cfef5","event":"Loot","category":"loot","px":277.7,"py":403.0,"ts_relative":0,"is_bot":false},{"user_id":"94d042cb-a0f2-45f3-bdca-42fab73cfef5","event":"Position","category":"move_human","px":270.2,"py":391.8,"ts_relative":0,"is_bot":false},{"user_id":"94d042cb-a0f2-45f3-bdca-42fab73cfef5","event":"Position","category":"move_human","px":281.2,"py":345.9,"ts_relative":0,"is_bot":false},{"user_id":"94d042cb-a0f2-45f3-bdca-42fab73cfef5","event":"Position","category":"move_human","px":246.6,"py":317.6,"ts_relative":0,"is_bot":false},{"user_id":"94d042cb-a0f2-45f3-bdca-42fab73cfef5","event":"Position","category":"move_human","px":289.8,"py":295.6,"ts_relative":0,"is_bot":false},{"user_id":"94d042cb-a0f2-45f3-bdca-42fab73cfef5","event":"Position","category":"move_human","px":345.1,"py":282.0,"ts_relative":0,"is_bot":false},{"user_id":"94d042cb-a0f2-45f3-bdca-42fab73cfef5","event":"Position","category":"move_human","px":384.1,"py":269.9,"ts_relative":0,"is_bot":false},{"user_id":"94d042cb-a0f2-45f3-bdca-42fab73cfef5","event":"Position","category":"move_human","px":389.6,"py":275.8,"ts_relative":0,"is_bot":false},{"user_id":"94d042cb-a0f2-45f3-bdca-42fab73cfef5","event":"Position","category":"move_human","px":377.8,"py":252.2,"ts_relative":0,"is_bot":false},{"user_id":"94d042cb-a0f2-45f3-bdca-42fab73cfef5","event":"Position","category":"move_human","px":381.3,"py":244.5,"ts_relative":0,"is_bot":false},{"user_id":"94d042cb-a0f2-45f3-bdca-42fab73cfef5","event":"Position","category":"move_human","px":380.0,"py":256.5,"ts_relative":0,"is_bot":false},{"user_id":"94d042cb-a0f2-45f3-bdca-42fab73cfef5","event":"Position","category":"move_human","px":415.6,"py":282.6,"ts_relative":0,"is_bot":false},{"user_id":"94d042cb-a0f2-45f3-bdca-42fab73cfef5","event":"Position","category":"move_human","px":448.6,"py":275.1,"ts_relative":0,"is_bot":false},{"user_id":"94d042cb-a0f2-45f3-bdca-42fab73cfef5","event":"Position","category":"move_human","px":447.0,"py":265.0,"ts_relative":0,"is_bot":false},{"user_id":"94d042cb-a0f2-45f3-bdca-42fab73cfef5","event":"Position","category":"move_human","px":438.8,"py":277.1,"ts_relative":0,"is_bot":false},{"user_id":"94d042cb-a0f2-45f3-bdca-42fab73cfef5","event":"Position","category":"move_human","px":423.7,"py":288.4,"ts_relative":0,"is_bot":false},{"user_id":"94d042cb-a0f2-45f3-bdca-42fab73cfef5","event":"Position","category":"move_human","px":443.6,"py":271.9,"ts_relative":0,"is_bot":false},{"user_id":"94d042cb-a0f2-45f3-bdca-42fab73cfef5","event":"Position","category":"move_human","px":452.1,"py":267.1,"ts_relative":0,"is_bot":false},{"user_id":"94d042cb-a0f2-45f3-bdca-42fab73cfef5","event":"Position","category":"move_human","px":438.9,"py":273.4,"ts_relative":0,"is_bot":false},{"user_id":"94d042cb-a0f2-45f3-bdca-42fab73cfef5","event":"Position","category":"move_human","px":445.1,"py":272.1,"ts_relative":0,"is_bot":false},{"user_id":"94d042cb-a0f2-45f3-bdca-42fab73cfef5","event":"Position","category":"move_human","px":437.3,"py":273.9,"ts_relative":0,"is_bot":false},{"user_id":"94d042cb-a0f2-45f3-bdca-42fab73cfef5","event":"BotKill","category":"combat","px":437.3,"py":273.9,"ts_relative":0,"is_bot":false},{"user_id":"94d042cb-a0f2-45f3-bdca-42fab73cfef5","event":"Loot","category":"loot","px":438.2,"py":265.0,"ts_relative":0,"is_bot":false},{"user_id":"94d042cb-a0f2-45f3-bdca-42fab73cfef5","event":"Position","category":"move_human","px":438.0,"py":264.6,"ts_relative":0,"is_bot":false},{"user_id":"94d042cb-a0f2-45f3-bdca-42fab73cfef5","event":"Loot","category":"loot","px":438.0,"py":264.6,"ts_relative":0,"is_bot":false},{"user_id":"94d042cb-a0f2-45f3-bdca-42fab73cfef5","event":"Loot","category":"loot","px":438.0,"py":264.6,"ts_relative":0,"is_bot":false},{"user_id":"94d042cb-a0f2-45f3-bdca-42fab73cfef5","event":"Loot","category":"loot","px":438.0,"py":264.6,"ts_relative":0,"is_bot":false},{"user_id":"94d042cb-a0f2-45f3-bdca-42fab73cfef5","event":"Position","category":"move_human","px":422.2,"py":280.9,"ts_relative":0,"is_bot":false},{"user_id":"94d042cb-a0f2-45f3-bdca-42fab73cfef5","event":"Position","category":"move_human","px":398.2,"py":306.1,"ts_relative":0,"is_bot":false},{"user_id":"94d042cb-a0f2-45f3-bdca-42fab73cfef5","event":"Position","category":"move_human","px":361.7,"py":343.3,"ts_relative":0,"is_bot":false},{"user_id":"94d042cb-a0f2-45f3-bdca-42fab73cfef5","event":"Position","category":"move_human","px":342.1,"py":393.8,"ts_relative":0,"is_bot":false},{"user_id":"94d042cb-a0f2-45f3-bdca-42fab73cfef5","event":"Position","category":"move_human","px":339.6,"py":427.6,"ts_relative":0,"is_bot":false},{"user_id":"94d042cb-a0f2-45f3-bdca-42fab73cfef5","event":"Position","category":"move_human","px":355.4,"py":439.4,"ts_relative":0,"is_bot":false},{"user_id":"94d042cb-a0f2-45f3-bdca-42fab73cfef5","event":"Position","category":"move_human","px":387.4,"py":440.3,"ts_relative":0,"is_bot":false},{"user_id":"94d042cb-a0f2-45f3-bdca-42fab73cfef5","event":"Position","category":"move_human","px":385.9,"py":481.8,"ts_relative":0,"is_bot":false},{"user_id":"94d042cb-a0f2-45f3-bdca-42fab73cfef5","event":"Loot","category":"loot","px":378.5,"py":482.4,"ts_relative":0,"is_bot":false},{"user_id":"94d042cb-a0f2-45f3-bdca-42fab73cfef5","event":"Loot","category":"loot","px":378.5,"py":482.4,"ts_relative":0,"is_bot":false},{"user_id":"94d042cb-a0f2-45f3-bdca-42fab73cfef5","event":"Position","category":"move_human","px":370.7,"py":493.5,"ts_relative":0,"is_bot":false},{"user_id":"94d042cb-a0f2-45f3-bdca-42fab73cfef5","event":"Loot","category":"loot","px":370.7,"py":493.5,"ts_relative":0,"is_bot":false},{"user_id":"94d042cb-a0f2-45f3-bdca-42fab73cfef5","event":"Position","category":"move_human","px":401.5,"py":494.7,"ts_relative":0,"is_bot":false},{"user_id":"94d042cb-a0f2-45f3-bdca-42fab73cfef5","event":"Position","category":"move_human","px":392.6,"py":534.2,"ts_relative":0,"is_bot":false},{"user_id":"94d042cb-a0f2-45f3-bdca-42fab73cfef5","event":"Position","category":"move_human","px":400.0,"py":576.4,"ts_relative":0,"is_bot":false},{"user_id":"94d042cb-a0f2-45f3-bdca-42fab73cfef5","event":"Position","category":"move_human","px":444.9,"py":593.9,"ts_relative":0,"is_bot":false},{"user_id":"94d042cb-a0f2-45f3-bdca-42fab73cfef5","event":"Position","category":"move_human","px":485.9,"py":615.3,"ts_relative":0,"is_bot":false},{"user_id":"94d042cb-a0f2-45f3-bdca-42fab73cfef5","event":"Loot","category":"loot","px":494.6,"py":613.4,"ts_relative":0,"is_bot":false},{"user_id":"94d042cb-a0f2-45f3-bdca-42fab73cfef5","event":"Position","category":"move_human","px":480.1,"py":600.8,"ts_relative":0,"is_bot":false},{"user_id":"94d042cb-a0f2-45f3-bdca-42fab73cfef5","event":"Position","category":"move_human","px":463.8,"py":603.7,"ts_relative":0,"is_bot":false},{"user_id":"94d042cb-a0f2-45f3-bdca-42fab73cfef5","event":"Position","category":"move_human","px":467.5,"py":601.7,"ts_relative":0,"is_bot":false},{"user_id":"94d042cb-a0f2-45f3-bdca-42fab73cfef5","event":"Position","category":"move_human","px":468.7,"py":610.1,"ts_relative":0,"is_bot":false},{"user_id":"94d042cb-a0f2-45f3-bdca-42fab73cfef5","event":"Loot","category":"loot","px":459.1,"py":628.6,"ts_relative":0,"is_bot":false},{"user_id":"94d042cb-a0f2-45f3-bdca-42fab73cfef5","event":"Position","category":"move_human","px":459.1,"py":628.6,"ts_relative":0,"is_bot":false},{"user_id":"94d042cb-a0f2-45f3-bdca-42fab73cfef5","event":"Position","category":"move_human","px":446.3,"py":619.9,"ts_relative":0,"is_bot":false},{"user_id":"94d042cb-a0f2-45f3-bdca-42fab73cfef5","event":"Position","category":"move_human","px":446.7,"py":601.4,"ts_relative":0,"is_bot":false},{"user_id":"94d042cb-a0f2-45f3-bdca-42fab73cfef5","event":"Loot","category":"loot","px":446.7,"py":601.4,"ts_relative":0,"is_bot":false},{"user_id":"94d042cb-a0f2-45f3-bdca-42fab73cfef5","event":"Position","category":"move_human","px":448.3,"py":620.0,"ts_relative":0,"is_bot":false},{"user_id":"94d042cb-a0f2-45f3-bdca-42fab73cfef5","event":"Position","category":"move_human","px":442.4,"py":614.8,"ts_relative":0,"is_bot":false},{"user_id":"94d042cb-a0f2-45f3-bdca-42fab73cfef5","event":"Position","category":"move_human","px":438.3,"py":602.8,"ts_relative":0,"is_bot":false},{"user_id":"94d042cb-a0f2-45f3-bdca-42fab73cfef5","event":"Position","category":"move_human","px":409.4,"py":619.0,"ts_relative":0,"is_bot":false},{"user_id":"94d042cb-a0f2-45f3-bdca-42fab73cfef5","event":"Position","category":"move_human","px":387.7,"py":658.0,"ts_relative":0,"is_bot":false},{"user_id":"94d042cb-a0f2-45f3-bdca-42fab73cfef5","event":"Position","category":"move_human","px":350.6,"py":689.4,"ts_relative":0,"is_bot":false},{"user_id":"94d042cb-a0f2-45f3-bdca-42fab73cfef5","event":"Position","category":"move_human","px":302.9,"py":701.4,"ts_relative":0,"is_bot":false},{"user_id":"94d042cb-a0f2-45f3-bdca-42fab73cfef5","event":"Position","category":"move_human","px":268.5,"py":711.3,"ts_relative":0,"is_bot":false},{"user_id":"94d042cb-a0f2-45f3-bdca-42fab73cfef5","event":"Position","category":"move_human","px":265.6,"py":716.8,"ts_relative":0,"is_bot":false}]}